Workbook

Sheet Inicio
A2: NeXo | Prospectos y correos
A3: Base local de negocios de La Dorada, Caldas, con borradores de correo personalizables por sector.
A5: Negocios | C5: Con correo publicado | E5: Sin correo publicado | G5: Categorías
B6: =COUNTA(Contactos!$B$5:$B$225) | D6: =COUNTIF(Contactos!$E$5:$E$225,"<>") | F6: =COUNTBLANK(Contactos!$E$5:$E$225) | H6: =COUNTA(Plantillas!$A$6:$A$15)
A8: Flujo de trabajo
A9: 1. Filtra | B9: En Contactos, usa los filtros de la tabla para elegir una categoría, correo disponible o estado.
A10: 2. Ajusta el mensaje | B10: Edita el asunto y cuerpo de cada sector en Plantillas. Los borradores de Contactos cambian automáticamente; {NEGOCIO} se sustituye por el nombre del prospecto.
A11: 3. Revisa los datos | B11: Confirma que el negocio siga activo, que el correo corresponda y que el contacto comercial sea apropiado antes de enviar.
A12: 4. Prepara la automatización | B12: Procesa solo filas con correo verificado, autorización comercial confirmada y estado Listo para enviar; después registra Enviado y la fecha para evitar duplicados.
A13: 5. Respeta bajas | B13: Si alguien pide no recibir más mensajes, cambia el estado a Dado de baja o No contactar y exclúyelo de cualquier campaña futura.
A14: WhatsApp | B14: Todos los permisos están pendientes según los archivos fuente. No uses teléfonos para publicidad por WhatsApp hasta registrar el consentimiento correspondiente.
A16: Cobertura y fuente
A17: Consolidación | B17: 221 negocios únicos integrados de los dos archivos recibidos; 96 correos publicados y 125 registros sin correo público.
A18: Consulta fuente | B18: La fecha de consulta de los archivos es 19-oct-2026. Las señales de actualidad y enlaces originales se conservan en Contactos.
A19: Validación | B19: La presencia de un contacto público no confirma que siga vigente ni que pueda usarse para cualquier campaña. Verifica cada registro y aplica las reglas de contacto y baja correspondientes.

Sheet Contactos
A2: Base de contactos de La Dorada
A3: Filtra por categoría o correo. Asunto y cuerpo salen de Plantillas; haz clic en la celda para copiar el texto completo. Las celdas amarillas son controles editables.
A4: ID | B4: Negocio | C4: Categoría de contacto | D4: Sector según fuente | E4: Correo público | F4: Teléfono público | G4: Dirección publicada | H4: Fecha de consulta | I4: Indicio de actualidad | J4: Fuente pública | K4: Observaciones de la fuente | L4: Asunto sugerido | M4: Cuerpo sugerido | N4: Validación del correo | O4: Autorización comercial | P4: Estado de campaña | Q4: Fecha de envío | R4: Resultado / notas | S4: WhatsApp autorizado
A5: NX-001 | B5: EL SOL DORADO | C5: Hoteles y hospedajes | D5: Hotel / hospedaje | E5: hotelsoldoradoladorada@gmail.com | F5: 3103726898 | G5: K 1 14 44 | H5: 46314 | I5: Sin señal de actualización específica en el registro fuente; verificar vigencia. | J5: https://www.datos.gov.co/w/m463-yj48/dneh-mcp2 | K5: Registro del directorio público de hoteles; confirmar vigencia y datos antes de contactar. Dirección conservada en el formato abreviado de la fuente. | Fuente: Prospectos_NeXo_La_Dorada.xlsx | L5: =IF($B5="","",SUBSTITUTE(INDEX(Plantillas!$B$6:$B$15,MATCH($C5,Plantillas!$A$6:$A$15,0)),"{NEGOCIO}",$B5)) | M5: =IF($B5="","",SUBSTITUTE(INDEX(Plantillas!$C$6:$C$15,MATCH($C5,Plantillas!$A$6:$A$15,0)),"{NEGOCIO}",$B5)) | N5: Pendiente de verificar | O5: Pendiente de revisar | P5: Enviado | Q5: 2026-10-21 14:02:23 | R5: Enviado con éxito a: hotelsoldoradoladorada@gmail.com | S5: Pendiente
A6: NX-002 | B6: MALL SANTANA DEL RÍO | C6: Hoteles y hospedajes | D6: Hotel / hospedaje | E6: reservas@hotelsantanadelrio.com | F6: 3126777777 | G6: C 13 K 1 | H6: 46314 | I6: Sin señal de actualización específica en el registro fuente; verificar vigencia. | J6: https://www.datos.gov.co/w/m463-yj48/dneh-mcp2 | K6: Registro del directorio público de hoteles; confirmar vigencia y datos antes de contactar. Dirección conservada en el formato abreviado de la fuente. | Fuente: Prospectos_NeXo_La_Dorada.xlsx | L6: =IF($B6="","",SUBSTITUTE(INDEX(Plantillas!$B$6:$B$15,MATCH($C6,Plantillas!$A$6:$A$15,0)),"{NEGOCIO}",$B6)) | M6: =IF($B6="","",SUBSTITUTE(INDEX(Plantillas!$C$6:$C$15,MATCH($C6,Plantillas!$A$6:$A$15,0)),"{NEGOCIO}",$B6)) | N6: Pendiente de verificar | O6: Pendiente de revisar | P6: Enviado | Q6: 2026-10-21 14:03:26 | R6: Enviado con éxito a: reservas@hotelsantanadelrio.com | S6: Pendiente
A7: NX-003 | B7: APARTAHOTEL AUTOMATICO | C7: Hoteles y hospedajes | D7: Hotel / hospedaje | E7: osorio1023@hotmail.com | F7: 3147936195 | G7: K 2 13 04 | H7: 46314 | I7: Sin señal de actualización específica en el registro fuente; verificar vigencia. | J7: https://www.datos.gov.co/w/m463-yj48/dneh-mcp2 | K7: Registro del directorio público de hoteles; confirmar vigencia y datos antes de contactar. Dirección conservada en el formato abreviado de la fuente. | Fuente: Prospectos_NeXo_La_Dorada.xlsx | L7: =IF($B7="","",SUBSTITUTE(INDEX(Plantillas!$B$6:$B$15,MATCH($C7,Plantillas!$A$6:$A$15,0)),"{NEGOCIO}",$B7)) | M7: =IF($B7="","",SUBSTITUTE(INDEX(Plantillas!$C$6:$C$15,MATCH($C7,Plantillas!$A$6:$A$15,0)),"{NEGOCIO}",$B7)) | N7: Pendiente de verificar | O7: Pendiente de revisar | P7: Pendiente de revisión | S7: Pendiente
A8: NX-004 | B8: SOROCAIMA | C8: Hoteles y hospedajes | D8: Hotel / hospedaje | E8: ivanchavarro@hotmail.com | F8: 3218072460 | G8: K 2 14 17 | H8: 46314 | I8: Sin señal de actualización específica en el registro fuente; verificar vigencia. | J8: https://www.datos.gov.co/w/m463-yj48/dneh-mcp2 | K8: Registro del directorio público de hoteles; confirmar vigencia y datos antes de contactar. Dirección conservada en el formato abreviado de la fuente. | Fuente: Prospectos_NeXo_La_Dorada.xlsx | L8: =IF($B8="","",SUBSTITUTE(INDEX(Plantillas!$B$6:$B$15,MATCH($C8,Plantillas!$A$6:$A$15,0)),"{NEGOCIO}",$B8)) | M8: =IF($B8="","",SUBSTITUTE(INDEX(Plantillas!$C$6:$C$15,MATCH($C8,Plantillas!$A$6:$A$15,0)),"{NEGOCIO}",$B8)) | N8: Pendiente de verificar | O8: Pendiente de revisar | P8: Pendiente de revisión | S8: Pendiente
A9: NX-005 | B9: RESORT COLOMBIA | C9: Hoteles y hospedajes | D9: Hotel / hospedaje | E9: resortcolombia@hotmail.com | F9: 3107685708 | G9: K 3 13 40 | H9: 46314 | I9: Sin señal de actualización específica en el registro fuente; verificar vigencia. | J9: https://www.datos.gov.co/w/m463-yj48/dneh-mcp2 | K9: Registro del directorio público de hoteles; confirmar vigencia y datos antes de contactar. Dirección conservada en el formato abreviado de la fuente. | Fuente: Prospectos_NeXo_La_Dorada.xlsx | L9: =IF($B9="","",SUBSTITUTE(INDEX(Plantillas!$B$6:$B$15,MATCH($C9,Plantillas!$A$6:$A$15,0)),"{NEGOCIO}",$B9)) | M9: =IF($B9="","",SUBSTITUTE(INDEX(Plantillas!$C$6:$C$15,MATCH($C9,Plantillas!$A$6:$A$15,0)),"{NEGOCIO}",$B9)) | N9: Pendiente de verificar | O9: Pendiente de revisar | P9: Pendiente de revisión | S9: Pendiente
A10: NX-006 | B10: EL MESON | C10: Hoteles y hospedajes | D10: Hotel / hospedaje | E10: gerencia@hotelelmeson.com | F10: 3146000000 | G10: K 3 15 61 | H10: 46314 | I10: Sin señal de actualización específica en el registro fuente; verificar vigencia. | J10: https://www.datos.gov.co/w/m463-yj48/dneh-mcp2 | K10: Registro del directorio público de hoteles; confirmar vigencia y datos antes de contactar. Dirección conservada en el formato abreviado de la fuente. | Fuente: Prospectos_NeXo_La_Dorada.xlsx | L10: =IF($B10="","",SUBSTITUTE(INDEX(Plantillas!$B$6:$B$15,MATCH($C10,Plantillas!$A$6:$A$15,0)),"{NEGOCIO}",$B10)) | M10: =IF($B10="","",SUBSTITUTE(INDEX(Plantillas!$C$6:$C$15,MATCH($C10,Plantillas!$A$6:$A$15,0)),"{NEGOCIO}",$B10)) | N10: Pendiente de verificar | O10: Pendiente de revisar | P10: Pendiente de revisión | S10: Pendiente
A11: NX-007 | B11: BOLÍVAR PLAZA | C11: Hoteles y hospedajes | D11: Hotel / hospedaje | E11: reservas@hotelesbolivarplaza.com | F11: 3218019705 | G11: C 16 2 38 | H11: 46314 | I11: Sin señal de actualización específica en el registro fuente; verificar vigencia. | J11: https://www.datos.gov.co/w/m463-yj48/dneh-mcp2 | K11: Registro del directorio público de hoteles; confirmar vigencia y datos antes de contactar. Dirección conservada en el formato abreviado de la fuente. | Fuente: Prospectos_NeXo_La_Dorada.xlsx | L11: =IF($B11="","",SUBSTITUTE(INDEX(Plantillas!$B$6:$B$15,MATCH($C11,Plantillas!$A$6:$A$15,0)),"{NEGOCIO}",$B11)) | M11: =IF($B11="","",SUBSTITUTE(INDEX(Plantillas!$C$6:$C$15,MATCH($C11,Plantillas!$A$6:$A$15,0)),"{NEGOCIO}",$B11)) | N11: Pendiente de verificar | O11: Pendiente de revisar | P11: Pendiente de revisión | S11: Pendiente
A12: NX-008 | B12: MI CASITA | C12: Hoteles y hospedajes | D12: Hotel / hospedaje | E12: hotelfamiliarmicasitajm1975@gmail.com | F12: 3138107714 | G12: C 16 2 56 | H12: 46314 | I12: Sin señal de actualización específica en el registro fuente; verificar vigencia. | J12: https://www.datos.gov.co/w/m463-yj48/dneh-mcp2 | K12: Registro del directorio público de hoteles; confirmar vigencia y datos antes de contactar. Dirección conservada en el formato abreviado de la fuente. | Fuente: Prospectos_NeXo_La_Dorada.xlsx | L12: =IF($B12="","",SUBSTITUTE(INDEX(Plantillas!$B$6:$B$15,MATCH($C12,Plantillas!$A$6:$A$15,0)),"{NEGOCIO}",$B12)) | M12: =IF($B12="","",SUBSTITUTE(INDEX(Plantillas!$C$6:$C$15,MATCH($C12,Plantillas!$A$6:$A$15,0)),"{NEGOCIO}",$B12)) | N12: Pendiente de verificar | O12: Pendiente de revisar | P12: Pendiente de revisión | S12: Pendiente
A13: NX-009 | B13: LUMARAC | C13: Hoteles y hospedajes | D13: Hotel / hospedaje | E13: niercusa@hotmail.com | F13: 3146516110 | G13: C 16 2 48 | H13: 46314 | I13: Sin señal de actualización específica en el registro fuente; verificar vigencia. | J13: https://www.datos.gov.co/w/m463-yj48/dneh-mcp2 | K13: Registro del directorio público de hoteles; confirmar vigencia y datos antes de contactar. Dirección conservada en el formato abreviado de la fuente. | Fuente: Prospectos_NeXo_La_Dorada.xlsx | L13: =IF($B13="","",SUBSTITUTE(INDEX(Plantillas!$B$6:$B$15,MATCH($C13,Plantillas!$A$6:$A$15,0)),"{NEGOCIO}",$B13)) | M13: =IF($B13="","",SUBSTITUTE(INDEX(Plantillas!$C$6:$C$15,MATCH($C13,Plantillas!$A$6:$A$15,0)),"{NEGOCIO}",$B13)) | N13: Pendiente de verificar | O13: Pendiente de revisar | P13: Pendiente de revisión | S13: Pendiente
A14: NX-010 | B14: EL PALACIO | C14: Hoteles y hospedajes | D14: Hotel / hospedaje | E14: robinsonagudelo2010@gmail.com | F14: 3228347900 | G14: K 2 16 25 | H14: 46314 | I14: Sin señal de actualización específica en el registro fuente; verificar vigencia. | J14: https://www.datos.gov.co/w/m463-yj48/dneh-mcp2 | K14: Registro del directorio público de hoteles; confirmar vigencia y datos antes de contactar. Dirección conservada en el formato abreviado de la fuente. | Fuente: Prospectos_NeXo_La_Dorada.xlsx | L14: =IF($B14="","",SUBSTITUTE(INDEX(Plantillas!$B$6:$B$15,MATCH($C14,Plantillas!$A$6:$A$15,0)),"{NEGOCIO}",$B14)) | M14: =IF($B14="","",SUBSTITUTE(INDEX(Plantillas!$C$6:$C$15,MATCH($C14,Plantillas!$A$6:$A$15,0)),"{NEGOCIO}",$B14)) | N14: Pendiente de verificar | O14: Pendiente de revisar | P14: Pendiente de revisión | S14: Pendiente
A15: NX-011 | B15: BELLA ISA | C15: Hoteles y hospedajes | D15: Hotel / hospedaje | E15: hotelbellaisa@gmail.com | F15: 3205579451 | G15: K 2 18 33 | H15: 46314 | I15: Sin señal de actualización específica en el registro fuente; verificar vigencia. | J15: https://www.datos.gov.co/w/m463-yj48/dneh-mcp2 | K15: Registro del directorio público de hoteles; confirmar vigencia y datos antes de contactar. Dirección conservada en el formato abreviado de la fuente. | Fuente: Prospectos_NeXo_La_Dorada.xlsx | L15: =IF($B15="","",SUBSTITUTE(INDEX(Plantillas!$B$6:$B$15,MATCH($C15,Plantillas!$A$6:$A$15,0)),"{NEGOCIO}",$B15)) | M15: =IF($B15="","",SUBSTITUTE(INDEX(Plantillas!$C$6:$C$15,MATCH($C15,Plantillas!$A$6:$A$15,0)),"{NEGOCIO}",$B15)) | N15: Pendiente de verificar | O15: Pendiente de revisar | P15: Pendiente de revisión | S15: Pendiente
A16: NX-012 | B16: COUNTRY PLAZA | C16: Hoteles y hospedajes | D16: Hotel / hospedaje | E16: jhonvivarez@gmail.com | F16: 3218020900 | G16: K 2 16 57 | H16: 46314 | I16: Sin señal de actualización específica en el registro fuente; verificar vigencia. | J16: https://www.datos.gov.co/w/m463-yj48/dneh-mcp2 | K16: Registro del directorio público de hoteles; confirmar vigencia y datos antes de contactar. Dirección conservada en el formato abreviado de la fuente. | Fuente: Prospectos_NeXo_La_Dorada.xlsx | L16: =IF($B16="","",SUBSTITUTE(INDEX(Plantillas!$B$6:$B$15,MATCH($C16,Plantillas!$A$6:$A$15,0)),"{NEGOCIO}",$B16)) | M16: =IF($B16="","",SUBSTITUTE(INDEX(Plantillas!$C$6:$C$15,MATCH($C16,Plantillas!$A$6:$A$15,0)),"{NEGOCIO}",$B16)) | N16: Pendiente de verificar | O16: Pendiente de revisar | P16: Pendiente de revisión | S16: Pendiente
A17: NX-013 | B17: RESIDENCIAS BOGOTÁ | C17: Hoteles y hospedajes | D17: Hotel / hospedaje | E17: evelioaaron12@gmail.com | F17: 3147027029 | G17: K 2 20 23 | H17: 46314 | I17: Sin señal de actualización específica en el registro fuente; verificar vigencia. | J17: https://www.datos.gov.co/w/m463-yj48/dneh-mcp2 | K17: Registro del directorio público de hoteles; confirmar vigencia y datos antes de contactar. Dirección conservada en el formato abreviado de la fuente. | Fuente: Prospectos_NeXo_La_Dorada.xlsx | L17: =IF($B17="","",SUBSTITUTE(INDEX(Plantillas!$B$6:$B$15,MATCH($C17,Plantillas!$A$6:$A$15,0)),"{NEGOCIO}",$B17)) | M17: =IF($B17="","",SUBSTITUTE(INDEX(Plantillas!$C$6:$C$15,MATCH($C17,Plantillas!$A$6:$A$15,0)),"{NEGOCIO}",$B17)) | N17: Pendiente de verificar | O17: Pendiente de revisar | P17: Pendiente de revisión | S17: Pendiente
A18: NX-014 | B18: RUTA DORADA | C18: Hoteles y hospedajes | D18: Hotel / hospedaje | F18: 3218007674 | G18: C 17 2 40 | H18: 46314 | I18: Sin señal de actualización específica en el registro fuente; verificar vigencia. | J18: https://www.datos.gov.co/w/m463-yj48/dneh-mcp2 | K18: Registro del directorio público de hoteles; confirmar vigencia y datos antes de contactar. Dirección conservada en el formato abreviado de la fuente. | Fuente: Prospectos_NeXo_La_Dorada.xlsx | L18: =IF($B18="","",SUBSTITUTE(INDEX(Plantillas!$B$6:$B$15,MATCH($C18,Plantillas!$A$6:$A$15,0)),"{NEGOCIO}",$B18)) | M18: =IF($B18="","",SUBSTITUTE(INDEX(Plantillas!$C$6:$C$15,MATCH($C18,Plantillas!$A$6:$A$15,0)),"{NEGOCIO}",$B18)) | N18: Sin correo público | O18: Pendiente de revisar | P18: Pendiente de revisión | S18: Pendiente
A19: NX-015 | B19: EL PORTAL DE LA DORADA | C19: Hoteles y hospedajes | D19: Hotel / hospedaje | E19: gerhotelelportaldeladorada@gmail.com | F19: 3218117925 | G19: K 3 17 43 | H19: 46314 | I19: Sin señal de actualización específica en el registro fuente; verificar vigencia. | J19: https://www.datos.gov.co/w/m463-yj48/dneh-mcp2 | K19: Registro del directorio público de hoteles; confirmar vigencia y datos antes de contactar. Dirección conservada en el formato abreviado de la fuente. Cotelco publica una variante de correo/dirección; verificar el dato. | Fuente: Prospectos_NeXo_La_Dorada.xlsx | L19: =IF($B19="","",SUBSTITUTE(INDEX(Plantillas!$B$6:$B$15,MATCH($C19,Plantillas!$A$6:$A$15,0)),"{NEGOCIO}",$B19)) | M19: =IF($B19="","",SUBSTITUTE(INDEX(Plantillas!$C$6:$C$15,MATCH($C19,Plantillas!$A$6:$A$15,0)),"{NEGOCIO}",$B19)) | N19: Pendiente de verificar | O19: Pendiente de revisar | P19: Pendiente de revisión | S19: Pendiente
A20: NX-016 | B20: EL PALMAR DE LA DORADA | C20: Hoteles y hospedajes | D20: Hotel / hospedaje | E20: olaya1953@hotmail.com | F20: 3116091174 | G20: SALIDA HONDA | H20: 46314 | I20: Sin señal de actualización específica en el registro fuente; verificar vigencia. | J20: https://www.datos.gov.co/w/m463-yj48/dneh-mcp2 | K20: Registro del directorio público de hoteles; confirmar vigencia y datos antes de contactar. Dirección conservada en el formato abreviado de la fuente. | Fuente: Prospectos_NeXo_La_Dorada.xlsx | L20: =IF($B20="","",SUBSTITUTE(INDEX(Plantillas!$B$6:$B$15,MATCH($C20,Plantillas!$A$6:$A$15,0)),"{NEGOCIO}",$B20)) | M20: =IF($B20="","",SUBSTITUTE(INDEX(Plantillas!$C$6:$C$15,MATCH($C20,Plantillas!$A$6:$A$15,0)),"{NEGOCIO}",$B20)) | N20: Pendiente de verificar | O20: Pendiente de revisar | P20: Pendiente de revisión | S20: Pendiente
A21: NX-017 | B21: LA MELISSA | C21: Hoteles y hospedajes | D21: Hotel / hospedaje | E21: lamelissa20040@yahoo.es | F21: 3103522280 | G21: C 11 K 15 | H21: 46314 | I21: Sin señal de actualización específica en el registro fuente; verificar vigencia. | J21: https://www.datos.gov.co/w/m463-yj48/dneh-mcp2 | K21: Registro del directorio público de hoteles; confirmar vigencia y datos antes de contactar. Dirección conservada en el formato abreviado de la fuente. | Fuente: Prospectos_NeXo_La_Dorada.xlsx | L21: =IF($B21="","",SUBSTITUTE(INDEX(Plantillas!$B$6:$B$15,MATCH($C21,Plantillas!$A$6:$A$15,0)),"{NEGOCIO}",$B21)) | M21: =IF($B21="","",SUBSTITUTE(INDEX(Plantillas!$C$6:$C$15,MATCH($C21,Plantillas!$A$6:$A$15,0)),"{NEGOCIO}",$B21)) | N21: Pendiente de verificar | O21: Pendiente de revisar | P21: Pendiente de revisión | S21: Pendiente
A22: NX-018 | B22: BRISAS DEL RECUERDO | C22: Hoteles y hospedajes | D22: Hotel / hospedaje | E22: osdumo@yahoo.es | F22: 3117914842 | G22: K 15 16 18 | H22: 46314 | I22: Sin señal de actualización específica en el registro fuente; verificar vigencia. | J22: https://www.datos.gov.co/w/m463-yj48/dneh-mcp2 | K22: Registro del directorio público de hoteles; confirmar vigencia y datos antes de contactar. Dirección conservada en el formato abreviado de la fuente. | Fuente: Prospectos_NeXo_La_Dorada.xlsx | L22: =IF($B22="","",SUBSTITUTE(INDEX(Plantillas!$B$6:$B$15,MATCH($C22,Plantillas!$A$6:$A$15,0)),"{NEGOCIO}",$B22)) | M22: =IF($B22="","",SUBSTITUTE(INDEX(Plantillas!$C$6:$C$15,MATCH($C22,Plantillas!$A$6:$A$15,0)),"{NEGOCIO}",$B22)) | N22: Pendiente de verificar | O22: Pendiente de revisar | P22: Pendiente de revisión | S22: Pendiente
A23: NX-019 | B23: LA MANSIÓN | C23: Hoteles y hospedajes | D23: Hotel / hospedaje | E23: deypepa@yahoo.es | F23: 3105436376 | G23: K 15 16 38 | H23: 46314 | I23: Sin señal de actualización específica en el registro fuente; verificar vigencia. | J23: https://www.datos.gov.co/w/m463-yj48/dneh-mcp2 | K23: Registro del directorio público de hoteles; confirmar vigencia y datos antes de contactar. Dirección conservada en el formato abreviado de la fuente. | Fuente: Prospectos_NeXo_La_Dorada.xlsx | L23: =IF($B23="","",SUBSTITUTE(INDEX(Plantillas!$B$6:$B$15,MATCH($C23,Plantillas!$A$6:$A$15,0)),"{NEGOCIO}",$B23)) | M23: =IF($B23="","",SUBSTITUTE(INDEX(Plantillas!$C$6:$C$15,MATCH($C23,Plantillas!$A$6:$A$15,0)),"{NEGOCIO}",$B23)) | N23: Pendiente de verificar | O23: Pendiente de revisar | P23: Pendiente de revisión | S23: Pendiente
A24: NX-020 | B24: ZONA TROPICAL | C24: Hoteles y hospedajes | D24: Hotel / hospedaje | E24: hotelzonatropical@hotmail.com | F24: 3117929210 | G24: C 11 12 27 | H24: 46314 | I24: Sin señal de actualización específica en el registro fuente; verificar vigencia. | J24: https://www.datos.gov.co/w/m463-yj48/dneh-mcp2 | K24: Registro del directorio público de hoteles; confirmar vigencia y datos antes de contactar. Dirección conservada en el formato abreviado de la fuente. | Fuente: Prospectos_NeXo_La_Dorada.xlsx | L24: =IF($B24="","",SUBSTITUTE(INDEX(Plantillas!$B$6:$B$15,MATCH($C24,Plantillas!$A$6:$A$15,0)),"{NEGOCIO}",$B24)) | M24: =IF($B24="","",SUBSTITUTE(INDEX(Plantillas!$C$6:$C$15,MATCH($C24,Plantillas!$A$6:$A$15,0)),"{NEGOCIO}",$B24)) | N24: Pendiente de verificar | O24: Pendiente de revisar | P24: Pendiente de revisión | S24: Pendiente
A25: NX-021 | B25: MONTANAR | C25: Hoteles y hospedajes | D25: Hotel / hospedaje | E25: montanarhotel@gmail.com | F25: 3108442641 | G25: C 10 7 46 | H25: 46314 | I25: Sin señal de actualización específica en el registro fuente; verificar vigencia. | J25: https://www.datos.gov.co/w/m463-yj48/dneh-mcp2 | K25: Registro del directorio público de hoteles; confirmar vigencia y datos antes de contactar. Dirección conservada en el formato abreviado de la fuente. | Fuente: Prospectos_NeXo_La_Dorada.xlsx | L25: =IF($B25="","",SUBSTITUTE(INDEX(Plantillas!$B$6:$B$15,MATCH($C25,Plantillas!$A$6:$A$15,0)),"{NEGOCIO}",$B25)) | M25: =IF($B25="","",SUBSTITUTE(INDEX(Plantillas!$C$6:$C$15,MATCH($C25,Plantillas!$A$6:$A$15,0)),"{NEGOCIO}",$B25)) | N25: Pendiente de verificar | O25: Pendiente de revisar | P25: Pendiente de revisión | S25: Pendiente
A26: NX-022 | B26: APARTAESTUDIOS CONFORT | C26: Hoteles y hospedajes | D26: Hotel / hospedaje | E26: hotelconfort2016@hotmail.com | F26: 3226866448 | G26: C 10 6 35 | H26: 46314 | I26: Sin señal de actualización específica en el registro fuente; verificar vigencia. | J26: https://www.datos.gov.co/w/m463-yj48/dneh-mcp2 | K26: Registro del directorio público de hoteles; confirmar vigencia y datos antes de contactar. Dirección conservada en el formato abreviado de la fuente. | Fuente: Prospectos_NeXo_La_Dorada.xlsx | L26: =IF($B26="","",SUBSTITUTE(INDEX(Plantillas!$B$6:$B$15,MATCH($C26,Plantillas!$A$6:$A$15,0)),"{NEGOCIO}",$B26)) | M26: =IF($B26="","",SUBSTITUTE(INDEX(Plantillas!$C$6:$C$15,MATCH($C26,Plantillas!$A$6:$A$15,0)),"{NEGOCIO}",$B26)) | N26: Pendiente de verificar | O26: Pendiente de revisar | P26: Pendiente de revisión | S26: Pendiente
A27: NX-023 | B27: MONTEVERDE | C27: Hoteles y hospedajes | D27: Hotel / hospedaje | E27: monteverdehotel1@hotmail.com | F27: 3127931922 | G27: K 6 10 43 | H27: 46314 | I27: Sin señal de actualización específica en el registro fuente; verificar vigencia. | J27: https://www.datos.gov.co/w/m463-yj48/dneh-mcp2 | K27: Registro del directorio público de hoteles; confirmar vigencia y datos antes de contactar. Dirección conservada en el formato abreviado de la fuente. | Fuente: Prospectos_NeXo_La_Dorada.xlsx | L27: =IF($B27="","",SUBSTITUTE(INDEX(Plantillas!$B$6:$B$15,MATCH($C27,Plantillas!$A$6:$A$15,0)),"{NEGOCIO}",$B27)) | M27: =IF($B27="","",SUBSTITUTE(INDEX(Plantillas!$C$6:$C$15,MATCH($C27,Plantillas!$A$6:$A$15,0)),"{NEGOCIO}",$B27)) | N27: Pendiente de verificar | O27: Pendiente de revisar | P27: Pendiente de revisión | S27: Pendiente
A28: NX-024 | B28: TRAMONTI | C28: Hoteles y hospedajes | D28: Hotel / hospedaje | E28: laura_naranjo25@hotmail.com | F28: 3116434714 | G28: K 4 10 51 | H28: 46314 | I28: Sin señal de actualización específica en el registro fuente; verificar vigencia. | J28: https://www.datos.gov.co/w/m463-yj48/dneh-mcp2 | K28: Registro del directorio público de hoteles; confirmar vigencia y datos antes de contactar. Dirección conservada en el formato abreviado de la fuente. | Fuente: Prospectos_NeXo_La_Dorada.xlsx | L28: =IF($B28="","",SUBSTITUTE(INDEX(Plantillas!$B$6:$B$15,MATCH($C28,Plantillas!$A$6:$A$15,0)),"{NEGOCIO}",$B28)) | M28: =IF($B28="","",SUBSTITUTE(INDEX(Plantillas!$C$6:$C$15,MATCH($C28,Plantillas!$A$6:$A$15,0)),"{NEGOCIO}",$B28)) | N28: Pendiente de verificar | O28: Pendiente de revisar | P28: Pendiente de revisión | S28: Pendiente
A29: NX-025 | B29: MI CHOCITA | C29: Hoteles y hospedajes | D29: Hotel / hospedaje | E29: hotelmichocitadorada@hotmail.com | F29: 3206339035 | G29: K 2 6 17 | H29: 46314 | I29: Sin señal de actualización específica en el registro fuente; verificar vigencia. | J29: https://www.datos.gov.co/w/m463-yj48/dneh-mcp2 | K29: Registro del directorio público de hoteles; confirmar vigencia y datos antes de contactar. Dirección conservada en el formato abreviado de la fuente. | Fuente: Prospectos_NeXo_La_Dorada.xlsx | L29: =IF($B29="","",SUBSTITUTE(INDEX(Plantillas!$B$6:$B$15,MATCH($C29,Plantillas!$A$6:$A$15,0)),"{NEGOCIO}",$B29)) | M29: =IF($B29="","",SUBSTITUTE(INDEX(Plantillas!$C$6:$C$15,MATCH($C29,Plantillas!$A$6:$A$15,0)),"{NEGOCIO}",$B29)) | N29: Pendiente de verificar | O29: Pendiente de revisar | P29: Pendiente de revisión | S29: Pendiente
A30: NX-026 | B30: DORADA PLAZA | C30: Hoteles y hospedajes | D30: Hotel / hospedaje | E30: hoteldoradaplaza@hotmail.com | F30: 3148627715 | G30: C 14 3 65 | H30: 46314 | I30: Sin señal de actualización específica en el registro fuente; verificar vigencia. | J30: https://www.datos.gov.co/w/m463-yj48/dneh-mcp2 | K30: Registro del directorio público de hoteles; confirmar vigencia y datos antes de contactar. Dirección conservada en el formato abreviado de la fuente. | Fuente: Prospectos_NeXo_La_Dorada.xlsx | L30: =IF($B30="","",SUBSTITUTE(INDEX(Plantillas!$B$6:$B$15,MATCH($C30,Plantillas!$A$6:$A$15,0)),"{NEGOCIO}",$B30)) | M30: =IF($B30="","",SUBSTITUTE(INDEX(Plantillas!$C$6:$C$15,MATCH($C30,Plantillas!$A$6:$A$15,0)),"{NEGOCIO}",$B30)) | N30: Pendiente de verificar | O30: Pendiente de revisar | P30: Pendiente de revisión | S30: Pendiente
... A72: NX-068 | B72: HOSPEDAJE DOÑA LUZ MILA | C72: Hoteles y hospedajes | D72: Hotel / hospedaje | E72: clausanalejo326@hotmail.com | F72: 3136283962 | G72: C 11 13 34 | H72: 46314 | I72: Sin señal de actualización específica en el registro fuente; verificar vigencia. | J72: https://www.datos.gov.co/w/m463-yj48/dneh-mcp2 | K72: Registro del directorio público de hoteles; confirmar vigencia y datos antes de contactar. Dirección conservada en el formato abreviado de la fuente. | Fuente: Prospectos_NeXo_La_Dorada.xlsx | L72: =IF($B72="","",SUBSTITUTE(INDEX(Plantillas!$B$6:$B$15,MATCH($C72,Plantillas!$A$6:$A$15,0)),"{NEGOCIO}",$B72)) | M72: =IF($B72="","",SUBSTITUTE(INDEX(Plantillas!$C$6:$C$15,MATCH($C72,Plantillas!$A$6:$A$15,0)),"{NEGOCIO}",$B72)) | N72: Pendiente de verificar | O72: Pendiente de revisar | P72: Pendiente de revisión | S72: Pendiente
A73: NX-069 | B73: RESIDENCIAS LAS MALVINAS | C73: Hoteles y hospedajes | D73: Hotel / hospedaje | F73: 3113013104 | G73: C 19 3 30 | H73: 46314 | I73: Sin señal de actualización específica en el registro fuente; verificar vigencia. | J73: https://www.datos.gov.co/w/m463-yj48/dneh-mcp2 | K73: Registro del directorio público de hoteles; confirmar vigencia y datos antes de contactar. Dirección conservada en el formato abreviado de la fuente. | Fuente: Prospectos_NeXo_La_Dorada.xlsx | L73: =IF($B73="","",SUBSTITUTE(INDEX(Plantillas!$B$6:$B$15,MATCH($C73,Plantillas!$A$6:$A$15,0)),"{NEGOCIO}",$B73)) | M73: =IF($B73="","",SUBSTITUTE(INDEX(Plantillas!$C$6:$C$15,MATCH($C73,Plantillas!$A$6:$A$15,0)),"{NEGOCIO}",$B73)) | N73: Sin correo público | O73: Pendiente de revisar | P73: Pendiente de revisión | S73: Pendiente
A74: NX-070 | B74: POSADA TURISTICA BUENAVISTA | C74: Hoteles y hospedajes | D74: Hotel / hospedaje | E74: apbbuenavista@gmail.com | F74: 3164050918 | G74: BUENAVISTA | H74: 46314 | I74: Sin señal de actualización específica en el registro fuente; verificar vigencia. | J74: https://www.datos.gov.co/w/m463-yj48/dneh-mcp2 | K74: Registro del directorio público de hoteles; confirmar vigencia y datos antes de contactar. Dirección conservada en el formato abreviado de la fuente. | Fuente: Prospectos_NeXo_La_Dorada.xlsx | L74: =IF($B74="","",SUBSTITUTE(INDEX(Plantillas!$B$6:$B$15,MATCH($C74,Plantillas!$A$6:$A$15,0)),"{NEGOCIO}",$B74)) | M74: =IF($B74="","",SUBSTITUTE(INDEX(Plantillas!$C$6:$C$15,MATCH($C74,Plantillas!$A$6:$A$15,0)),"{NEGOCIO}",$B74)) | N74: Pendiente de verificar | O74: Pendiente de revisar | P74: Pendiente de revisión | S74: Pendiente
A75: NX-071 | B75: CABAÑA DE GEORGE | C75: Hoteles y hospedajes | D75: Hotel / hospedaje | F75: 3146019734 | G75: LA HABANA | H75: 46314 | I75: Sin señal de actualización específica en el registro fuente; verificar vigencia. | J75: https://www.datos.gov.co/w/m463-yj48/dneh-mcp2 | K75: Registro del directorio público de hoteles; confirmar vigencia y datos antes de contactar. Dirección conservada en el formato abreviado de la fuente. | Fuente: Prospectos_NeXo_La_Dorada.xlsx | L75: =IF($B75="","",SUBSTITUTE(INDEX(Plantillas!$B$6:$B$15,MATCH($C75,Plantillas!$A$6:$A$15,0)),"{NEGOCIO}",$B75)) | M75: =IF($B75="","",SUBSTITUTE(INDEX(Plantillas!$C$6:$C$15,MATCH($C75,Plantillas!$A$6:$A$15,0)),"{NEGOCIO}",$B75)) | N75: Sin correo público | O75: Pendiente de revisar | P75: Pendiente de revisión | S75: Pendiente
A76: NX-072 | B76: CABAÑA VILLA HERMOSA | C76: Hoteles y hospedajes | D76: Hotel / hospedaje | F76: 3206361169 | G76: LA HABANA | H76: 46314 | I76: Sin señal de actualización específica en el registro fuente; verificar vigencia. | J76: https://www.datos.gov.co/w/m463-yj48/dneh-mcp2 | K76: Registro del directorio público de hoteles; confirmar vigencia y datos antes de contactar. Dirección conservada en el formato abreviado de la fuente. | Fuente: Prospectos_NeXo_La_Dorada.xlsx | L76: =IF($B76="","",SUBSTITUTE(INDEX(Plantillas!$B$6:$B$15,MATCH($C76,Plantillas!$A$6:$A$15,0)),"{NEGOCIO}",$B76)) | M76: =IF($B76="","",SUBSTITUTE(INDEX(Plantillas!$C$6:$C$15,MATCH($C76,Plantillas!$A$6:$A$15,0)),"{NEGOCIO}",$B76)) | N76: Sin correo público | O76: Pendiente de revisar | P76: Pendiente de revisión | S76: Pendiente
A77: NX-073 | B77: CABAÑA SOL Y MIEL | C77: Hoteles y hospedajes | D77: Hotel / hospedaje | E77: ov870904@gmail.com | F77: 3108237675 | G77: LA HABANA | H77: 46314 | I77: Sin señal de actualización específica en el registro fuente; verificar vigencia. | J77: https://www.datos.gov.co/w/m463-yj48/dneh-mcp2 | K77: Registro del directorio público de hoteles; confirmar vigencia y datos antes de contactar. Dirección conservada en el formato abreviado de la fuente. | Fuente: Prospectos_NeXo_La_Dorada.xlsx | L77: =IF($B77="","",SUBSTITUTE(INDEX(Plantillas!$B$6:$B$15,MATCH($C77,Plantillas!$A$6:$A$15,0)),"{NEGOCIO}",$B77)) | M77: =IF($B77="","",SUBSTITUTE(INDEX(Plantillas!$C$6:$C$15,MATCH($C77,Plantillas!$A$6:$A$15,0)),"{NEGOCIO}",$B77)) | N77: Pendiente de verificar | O77: Pendiente de revisar | P77: Pendiente de revisión | S77: Pendiente
A78: NX-074 | B78: HOTEL LA PARCELA | C78: Hoteles y hospedajes | D78: Hotel / hospedaje | E78: holamillo@gmail.com | F78: 3148357836 | G78: GUARINOCITO | H78: 46314 | I78: Sin señal de actualización específica en el registro fuente; verificar vigencia. | J78: https://www.datos.gov.co/w/m463-yj48/dneh-mcp2 | K78: Registro del directorio público de hoteles; confirmar vigencia y datos antes de contactar. Dirección conservada en el formato abreviado de la fuente. | Fuente: Prospectos_NeXo_La_Dorada.xlsx | L78: =IF($B78="","",SUBSTITUTE(INDEX(Plantillas!$B$6:$B$15,MATCH($C78,Plantillas!$A$6:$A$15,0)),"{NEGOCIO}",$B78)) | M78: =IF($B78="","",SUBSTITUTE(INDEX(Plantillas!$C$6:$C$15,MATCH($C78,Plantillas!$A$6:$A$15,0)),"{NEGOCIO}",$B78)) | N78: Pendiente de verificar | O78: Pendiente de revisar | P78: Pendiente de revisión | S78: Pendiente
A79: NX-075 | B79: RESIDENCIAS MONACO | C79: Hoteles y hospedajes | D79: Hotel / hospedaje | F79: 3148569021 | G79: K 6 14 26 | H79: 46314 | I79: Sin señal de actualización específica en el registro fuente; verificar vigencia. | J79: https://www.datos.gov.co/w/m463-yj48/dneh-mcp2 | K79: Registro del directorio público de hoteles; confirmar vigencia y datos antes de contactar. Dirección conservada en el formato abreviado de la fuente. | Fuente: Prospectos_NeXo_La_Dorada.xlsx | L79: =IF($B79="","",SUBSTITUTE(INDEX(Plantillas!$B$6:$B$15,MATCH($C79,Plantillas!$A$6:$A$15,0)),"{NEGOCIO}",$B79)) | M79: =IF($B79="","",SUBSTITUTE(INDEX(Plantillas!$C$6:$C$15,MATCH($C79,Plantillas!$A$6:$A$15,0)),"{NEGOCIO}",$B79)) | N79: Sin correo público | O79: Pendiente de revisar | P79: Pendiente de revisión | S79: Pendiente
A80: NX-076 | B80: RESIDENCIAS ROMA | C80: Hoteles y hospedajes | D80: Hotel / hospedaje | F80: 3218469765 | G80: K 3 16 37 | H80: 46314 | I80: Sin señal de actualización específica en el registro fuente; verificar vigencia. | J80: https://www.datos.gov.co/w/m463-yj48/dneh-mcp2 | K80: Registro del directorio público de hoteles; confirmar vigencia y datos antes de contactar. Dirección conservada en el formato abreviado de la fuente. | Fuente: Prospectos_NeXo_La_Dorada.xlsx | L80: =IF($B80="","",SUBSTITUTE(INDEX(Plantillas!$B$6:$B$15,MATCH($C80,Plantillas!$A$6:$A$15,0)),"{NEGOCIO}",$B80)) | M80: =IF($B80="","",SUBSTITUTE(INDEX(Plantillas!$C$6:$C$15,MATCH($C80,Plantillas!$A$6:$A$15,0)),"{NEGOCIO}",$B80)) | N80: Sin correo público | O80: Pendiente de revisar | P80: Pendiente de revisión | S80: Pendiente
A81: NX-077 | B81: LA AURORA FAMILIAR | C81: Hoteles y hospedajes | D81: Hotel / hospedaje | E81: hotelfamiliarlaaurora@hotmail.com | F81: 3113094800 | G81: K 6 46 18 | H81: 46314 | I81: Sin señal de actualización específica en el registro fuente; verificar vigencia. | J81: https://www.datos.gov.co/w/m463-yj48/dneh-mcp2 | K81: Registro del directorio público de hoteles; confirmar vigencia y datos antes de contactar. Dirección conservada en el formato abreviado de la fuente. | Fuente: Prospectos_NeXo_La_Dorada.xlsx | L81: =IF($B81="","",SUBSTITUTE(INDEX(Plantillas!$B$6:$B$15,MATCH($C81,Plantillas!$A$6:$A$15,0)),"{NEGOCIO}",$B81)) | M81: =IF($B81="","",SUBSTITUTE(INDEX(Plantillas!$C$6:$C$15,MATCH($C81,Plantillas!$A$6:$A$15,0)),"{NEGOCIO}",$B81)) | N81: Pendiente de verificar | O81: Pendiente de revisar | P81: Pendiente de revisión | S81: Pendiente
A82: NX-078 | B82: LAS ACACIAS DE CALDAS | C82: Hoteles y hospedajes | D82: Hotel / hospedaje | E82: tatto55_@gmail.com | F82: 3107488357 | G82: C 14 5 31 | H82: 46314 | I82: Sin señal de actualización específica en el registro fuente; verificar vigencia. | J82: https://www.datos.gov.co/w/m463-yj48/dneh-mcp2 | K82: Registro del directorio público de hoteles; confirmar vigencia y datos antes de contactar. Dirección conservada en el formato abreviado de la fuente. | Fuente: Prospectos_NeXo_La_Dorada.xlsx | L82: =IF($B82="","",SUBSTITUTE(INDEX(Plantillas!$B$6:$B$15,MATCH($C82,Plantillas!$A$6:$A$15,0)),"{NEGOCIO}",$B82)) | M82: =IF($B82="","",SUBSTITUTE(INDEX(Plantillas!$C$6:$C$15,MATCH($C82,Plantillas!$A$6:$A$15,0)),"{NEGOCIO}",$B82)) | N82: Pendiente de verificar | O82: Pendiente de revisar | P82: Pendiente de revisión | S82: Pendiente
A83: NX-079 | B83: RESIDENCIAS DORADA | C83: Hoteles y hospedajes | D83: Hotel / hospedaje | E83: aidafer02@hotmail.com | F83: 3113688094 | G83: K 5 14 08 | H83: 46314 | I83: Sin señal de actualización específica en el registro fuente; verificar vigencia. | J83: https://www.datos.gov.co/w/m463-yj48/dneh-mcp2 | K83: Registro del directorio público de hoteles; confirmar vigencia y datos antes de contactar. Dirección conservada en el formato abreviado de la fuente. | Fuente: Prospectos_NeXo_La_Dorada.xlsx | L83: =IF($B83="","",SUBSTITUTE(INDEX(Plantillas!$B$6:$B$15,MATCH($C83,Plantillas!$A$6:$A$15,0)),"{NEGOCIO}",$B83)) | M83: =IF($B83="","",SUBSTITUTE(INDEX(Plantillas!$C$6:$C$15,MATCH($C83,Plantillas!$A$6:$A$15,0)),"{NEGOCIO}",$B83)) | N83: Pendiente de verificar | O83: Pendiente de revisar | P83: Pendiente de revisión | S83: Pendiente
A84: NX-080 | B84: CENTRAL LA DORADA | C84: Hoteles y hospedajes | D84: Hotel / hospedaje | E84: francybravorojas2014@hotmail.com | F84: 3113541898 | G84: C 16 3 37 | H84: 46314 | I84: Sin señal de actualización específica en el registro fuente; verificar vigencia. | J84: https://www.datos.gov.co/w/m463-yj48/dneh-mcp2 | K84: Registro del directorio público de hoteles; confirmar vigencia y datos antes de contactar. Dirección conservada en el formato abreviado de la fuente. | Fuente: Prospectos_NeXo_La_Dorada.xlsx | L84: =IF($B84="","",SUBSTITUTE(INDEX(Plantillas!$B$6:$B$15,MATCH($C84,Plantillas!$A$6:$A$15,0)),"{NEGOCIO}",$B84)) | M84: =IF($B84="","",SUBSTITUTE(INDEX(Plantillas!$C$6:$C$15,MATCH($C84,Plantillas!$A$6:$A$15,0)),"{NEGOCIO}",$B84)) | N84: Pendiente de verificar | O84: Pendiente de revisar | P84: Pendiente de revisión | S84: Pendiente
A85: NX-081 | B85: VILLA DEL RÍO MAGDALENA | C85: Hoteles y hospedajes | D85: Hotel / hospedaje | E85: motopaisa123@hotmail.com | F85: 3208499272 | G85: K 3 16 49 | H85: 46314 | I85: Sin señal de actualización específica en el registro fuente; verificar vigencia. | J85: https://www.datos.gov.co/w/m463-yj48/dneh-mcp2 | K85: Registro del directorio público de hoteles; confirmar vigencia y datos antes de contactar. Dirección conservada en el formato abreviado de la fuente. | Fuente: Prospectos_NeXo_La_Dorada.xlsx | L85: =IF($B85="","",SUBSTITUTE(INDEX(Plantillas!$B$6:$B$15,MATCH($C85,Plantillas!$A$6:$A$15,0)),"{NEGOCIO}",$B85)) | M85: =IF($B85="","",SUBSTITUTE(INDEX(Plantillas!$C$6:$C$15,MATCH($C85,Plantillas!$A$6:$A$15,0)),"{NEGOCIO}",$B85)) | N85: Pendiente de verificar | O85: Pendiente de revisar | P85: Pendiente de revisión | S85: Pendiente
A86: NX-082 | B86: HOTEL REFUGIO EN EL CAMINO | C86: Hoteles y hospedajes | D86: Hotel / hospedaje | F86: 3105436376 | G86: K 5 13 | H86: 46314 | I86: Sin señal de actualización específica en el registro fuente; verificar vigencia. | J86: https://www.datos.gov.co/w/m463-yj48/dneh-mcp2 | K86: Registro del directorio público de hoteles; confirmar vigencia y datos antes de contactar. Dirección conservada en el formato abreviado de la fuente. | Fuente: Prospectos_NeXo_La_Dorada.xlsx | L86: =IF($B86="","",SUBSTITUTE(INDEX(Plantillas!$B$6:$B$15,MATCH($C86,Plantillas!$A$6:$A$15,0)),"{NEGOCIO}",$B86)) | M86: =IF($B86="","",SUBSTITUTE(INDEX(Plantillas!$C$6:$C$15,MATCH($C86,Plantillas!$A$6:$A$15,0)),"{NEGOCIO}",$B86)) | N86: Sin correo público | O86: Pendiente de revisar | P86: Pendiente de revisión | S86: Pendiente
A87: NX-083 | B87: HOTEL BRISAS DEL MAGDALENA | C87: Hoteles y hospedajes | D87: Hotel / hospedaje | E87: henrvasv@hotmail.com | F87: 3007342075 | G87: K 2 5 61 | H87: 46314 | I87: Sin señal de actualización específica en el registro fuente; verificar vigencia. | J87: https://www.datos.gov.co/w/m463-yj48/dneh-mcp2 | K87: Registro del directorio público de hoteles; confirmar vigencia y datos antes de contactar. Dirección conservada en el formato abreviado de la fuente. | Fuente: Prospectos_NeXo_La_Dorada.xlsx | L87: =IF($B87="","",SUBSTITUTE(INDEX(Plantillas!$B$6:$B$15,MATCH($C87,Plantillas!$A$6:$A$15,0)),"{NEGOCIO}",$B87)) | M87: =IF($B87="","",SUBSTITUTE(INDEX(Plantillas!$C$6:$C$15,MATCH($C87,Plantillas!$A$6:$A$15,0)),"{NEGOCIO}",$B87)) | N87: Pendiente de verificar | O87: Pendiente de revisar | P87: Pendiente de revisión | S87: Pendiente
A88: NX-084 | B88: HOSPEDAJE MARACANÁ | C88: Hoteles y hospedajes | D88: Hotel / hospedaje | F88: 3147997326 | G88: C 16 5 31 | H88: 46314 | I88: Sin señal de actualización específica en el registro fuente; verificar vigencia. | J88: https://www.datos.gov.co/w/m463-yj48/dneh-mcp2 | K88: Registro del directorio público de hoteles; confirmar vigencia y datos antes de contactar. Dirección conservada en el formato abreviado de la fuente. | Fuente: Prospectos_NeXo_La_Dorada.xlsx | L88: =IF($B88="","",SUBSTITUTE(INDEX(Plantillas!$B$6:$B$15,MATCH($C88,Plantillas!$A$6:$A$15,0)),"{NEGOCIO}",$B88)) | M88: =IF($B88="","",SUBSTITUTE(INDEX(Plantillas!$C$6:$C$15,MATCH($C88,Plantillas!$A$6:$A$15,0)),"{NEGOCIO}",$B88)) | N88: Sin correo público | O88: Pendiente de revisar | P88: Pendiente de revisión | S88: Pendiente
A89: NX-085 | B89: RESIDENCIAS PLAZA | C89: Hoteles y hospedajes | D89: Hotel / hospedaje | F89: 3137314913 | G89: K 6 15 39 | H89: 46314 | I89: Sin señal de actualización específica en el registro fuente; verificar vigencia. | J89: https://www.datos.gov.co/w/m463-yj48/dneh-mcp2 | K89: Registro del directorio público de hoteles; confirmar vigencia y datos antes de contactar. Dirección conservada en el formato abreviado de la fuente. | Fuente: Prospectos_NeXo_La_Dorada.xlsx | L89: =IF($B89="","",SUBSTITUTE(INDEX(Plantillas!$B$6:$B$15,MATCH($C89,Plantillas!$A$6:$A$15,0)),"{NEGOCIO}",$B89)) | M89: =IF($B89="","",SUBSTITUTE(INDEX(Plantillas!$C$6:$C$15,MATCH($C89,Plantillas!$A$6:$A$15,0)),"{NEGOCIO}",$B89)) | N89: Sin correo público | O89: Pendiente de revisar | P89: Pendiente de revisión | S89: Pendiente
A90: NX-086 | B90: RESDIENCIAS ALCALA | C90: Hoteles y hospedajes | D90: Hotel / hospedaje | G90: GUARINOCITO | H90: 46314 | I90: Sin señal de actualización específica en el registro fuente; verificar vigencia. | J90: https://www.datos.gov.co/w/m463-yj48/dneh-mcp2 | K90: Registro del directorio público de hoteles; confirmar vigencia y datos antes de contactar. Dirección conservada en el formato abreviado de la fuente. | Fuente: Prospectos_NeXo_La_Dorada.xlsx | L90: =IF($B90="","",SUBSTITUTE(INDEX(Plantillas!$B$6:$B$15,MATCH($C90,Plantillas!$A$6:$A$15,0)),"{NEGOCIO}",$B90)) | M90: =IF($B90="","",SUBSTITUTE(INDEX(Plantillas!$C$6:$C$15,MATCH($C90,Plantillas!$A$6:$A$15,0)),"{NEGOCIO}",$B90)) | N90: Sin correo público | O90: Pendiente de revisar | P90: Pendiente de revisión | S90: Pendiente
A91: NX-087 | B91: RESIDENCIAS VERSALLES | C91: Hoteles y hospedajes | D91: Hotel / hospedaje | E91: reycast32@gmail.com | F91: 3104733995 | G91: C 18 4 58 | H91: 46314 | I91: Sin señal de actualización específica en el registro fuente; verificar vigencia. | J91: https://www.datos.gov.co/w/m463-yj48/dneh-mcp2 | K91: Registro del directorio público de hoteles; confirmar vigencia y datos antes de contactar. Dirección conservada en el formato abreviado de la fuente. | Fuente: Prospectos_NeXo_La_Dorada.xlsx | L91: =IF($B91="","",SUBSTITUTE(INDEX(Plantillas!$B$6:$B$15,MATCH($C91,Plantillas!$A$6:$A$15,0)),"{NEGOCIO}",$B91)) | M91: =IF($B91="","",SUBSTITUTE(INDEX(Plantillas!$C$6:$C$15,MATCH($C91,Plantillas!$A$6:$A$15,0)),"{NEGOCIO}",$B91)) | N91: Pendiente de verificar | O91: Pendiente de revisar | P91: Pendiente de revisión | S91: Pendiente
A92: NX-088 | B92: ECOPARCHE - TUKU TRIPS CAMPAMENTO | C92: Hoteles y hospedajes | D92: Hotel / hospedaje | E92: tukutrips@gmail.com | F92: 3128036009 | G92: FINCA LA CANTERA | H92: 46314 | I92: Sin señal de actualización específica en el registro fuente; verificar vigencia. | J92: https://www.datos.gov.co/w/m463-yj48/dneh-mcp2 | K92: Registro del directorio público de hoteles; confirmar vigencia y datos antes de contactar. Dirección conservada en el formato abreviado de la fuente. | Fuente: Prospectos_NeXo_La_Dorada.xlsx | L92: =IF($B92="","",SUBSTITUTE(INDEX(Plantillas!$B$6:$B$15,MATCH($C92,Plantillas!$A$6:$A$15,0)),"{NEGOCIO}",$B92)) | M92: =IF($B92="","",SUBSTITUTE(INDEX(Plantillas!$C$6:$C$15,MATCH($C92,Plantillas!$A$6:$A$15,0)),"{NEGOCIO}",$B92)) | N92: Pendiente de verificar | O92: Pendiente de revisar | P92: Pendiente de revisión | S92: Pendiente
A93: NX-089 | B93: HOTEL MARIIOS | C93: Hoteles y hospedajes | D93: Hotel / hospedaje | F93: 3108788729 | G93: C 13 3 50 | H93: 46314 | I93: Sin señal de actualización específica en el registro fuente; verificar vigencia. | J93: https://www.datos.gov.co/w/m463-yj48/dneh-mcp2 | K93: Registro del directorio público de hoteles; confirmar vigencia y datos antes de contactar. Dirección conservada en el formato abreviado de la fuente. | Fuente: Prospectos_NeXo_La_Dorada.xlsx | L93: =IF($B93="","",SUBSTITUTE(INDEX(Plantillas!$B$6:$B$15,MATCH($C93,Plantillas!$A$6:$A$15,0)),"{NEGOCIO}",$B93)) | M93: =IF($B93="","",SUBSTITUTE(INDEX(Plantillas!$C$6:$C$15,MATCH($C93,Plantillas!$A$6:$A$15,0)),"{NEGOCIO}",$B93)) | N93: Sin correo público | O93: Pendiente de revisar | P93: Pendiente de revisión | S93: Pendiente
A94: NX-090 | B94: HOTEL PARIS MC | C94: Hoteles y hospedajes | D94: Hotel / hospedaje | E94: ivancardonacarlos@gmail.com | F94: 3235874679 | G94: C 10B K 6 | H94: 46314 | I94: Sin señal de actualización específica en el registro fuente; verificar vigencia. | J94: https://www.datos.gov.co/w/m463-yj48/dneh-mcp2 | K94: Registro del directorio público de hoteles; confirmar vigencia y datos antes de contactar. Dirección conservada en el formato abreviado de la fuente. | Fuente: Prospectos_NeXo_La_Dorada.xlsx | L94: =IF($B94="","",SUBSTITUTE(INDEX(Plantillas!$B$6:$B$15,MATCH($C94,Plantillas!$A$6:$A$15,0)),"{NEGOCIO}",$B94)) | M94: =IF($B94="","",SUBSTITUTE(INDEX(Plantillas!$C$6:$C$15,MATCH($C94,Plantillas!$A$6:$A$15,0)),"{NEGOCIO}",$B94)) | N94: Pendiente de verificar | O94: Pendiente de revisar | P94: Pendiente de revisión | S94: Pendiente
A95: NX-091 | B95: HOTEL SAN RAFAEL | C95: Hoteles y hospedajes | D95: Hotel / hospedaje | F95: 3127343959 | G95: GUARINOCITO | H95: 46314 | I95: Sin señal de actualización específica en el registro fuente; verificar vigencia. | J95: https://www.datos.gov.co/w/m463-yj48/dneh-mcp2 | K95: Registro del directorio público de hoteles; confirmar vigencia y datos antes de contactar. Dirección conservada en el formato abreviado de la fuente. | Fuente: Prospectos_NeXo_La_Dorada.xlsx | L95: =IF($B95="","",SUBSTITUTE(INDEX(Plantillas!$B$6:$B$15,MATCH($C95,Plantillas!$A$6:$A$15,0)),"{NEGOCIO}",$B95)) | M95: =IF($B95="","",SUBSTITUTE(INDEX(Plantillas!$C$6:$C$15,MATCH($C95,Plantillas!$A$6:$A$15,0)),"{NEGOCIO}",$B95)) | N95: Sin correo público | O95: Pendiente de revisar | P95: Pendiente de revisión | S95: Pendiente
A96: NX-092 | B96: RESIDENCIAS EDS GUARINOCITO | C96: Hoteles y hospedajes | D96: Hotel / hospedaje | G96: GUARINOCITO | H96: 46314 | I96: Sin señal de actualización específica en el registro fuente; verificar vigencia. | J96: https://www.datos.gov.co/w/m463-yj48/dneh-mcp2 | K96: Registro del directorio público de hoteles; confirmar vigencia y datos antes de contactar. Dirección conservada en el formato abreviado de la fuente. | Fuente: Prospectos_NeXo_La_Dorada.xlsx | L96: =IF($B96="","",SUBSTITUTE(INDEX(Plantillas!$B$6:$B$15,MATCH($C96,Plantillas!$A$6:$A$15,0)),"{NEGOCIO}",$B96)) | M96: =IF($B96="","",SUBSTITUTE(INDEX(Plantillas!$C$6:$C$15,MATCH($C96,Plantillas!$A$6:$A$15,0)),"{NEGOCIO}",$B96)) | N96: Sin correo público | O96: Pendiente de revisar | P96: Pendiente de revisión | S96: Pendiente
A97: NX-093 | B97: CABAÑAS VILLA DILIA | C97: Hoteles y hospedajes | D97: Hotel / hospedaje | F97: 3206868747 | G97: PURNIO | H97: 46314 | I97: Sin señal de actualización específica en el registro fuente; verificar vigencia. | J97: https://www.datos.gov.co/w/m463-yj48/dneh-mcp2 | K97: Registro del directorio público de hoteles; confirmar vigencia y datos antes de contactar. Dirección conservada en el formato abreviado de la fuente. | Fuente: Prospectos_NeXo_La_Dorada.xlsx | L97: =IF($B97="","",SUBSTITUTE(INDEX(Plantillas!$B$6:$B$15,MATCH($C97,Plantillas!$A$6:$A$15,0)),"{NEGOCIO}",$B97)) | M97: =IF($B97="","",SUBSTITUTE(INDEX(Plantillas!$C$6:$C$15,MATCH($C97,Plantillas!$A$6:$A$15,0)),"{NEGOCIO}",$B97)) | N97: Sin correo público | O97: Pendiente de revisar | P97: Pendiente de revisión | S97: Pendiente
A98: NX-094 | B98: LA MILAGROSA | C98: Hoteles y hospedajes | D98: Hotel / hospedaje | F98: 3148858974 | G98: HUMADERA | H98: 46314 | I98: Sin señal de actualización específica en el registro fuente; verificar vigencia. | J98: https://www.datos.gov.co/w/m463-yj48/dneh-mcp2 | K98: Registro del directorio público de hoteles; confirmar vigencia y datos antes de contactar. Dirección conservada en el formato abreviado de la fuente. | Fuente: Prospectos_NeXo_La_Dorada.xlsx | L98: =IF($B98="","",SUBSTITUTE(INDEX(Plantillas!$B$6:$B$15,MATCH($C98,Plantillas!$A$6:$A$15,0)),"{NEGOCIO}",$B98)) | M98: =IF($B98="","",SUBSTITUTE(INDEX(Plantillas!$C$6:$C$15,MATCH($C98,Plantillas!$A$6:$A$15,0)),"{NEGOCIO}",$B98)) | N98: Sin correo público | O98: Pendiente de revisar | P98: Pendiente de revisión | S98: Pendiente
A99: NX-095 | B99: REFUGIO MONTE OSCURO | C99: Hoteles y hospedajes | D99: Hotel / hospedaje | E99: monteoscurosanmiguel@gmail.com | F99: 3148419269 | G99: LA ATARRAYA | H99: 46314 | I99: Sin señal de actualización específica en el registro fuente; verificar vigencia. | J99: https://www.datos.gov.co/w/m463-yj48/dneh-mcp2 | K99: Registro del directorio público de hoteles; confirmar vigencia y datos antes de contactar. Dirección conservada en el formato abreviado de la fuente. | Fuente: Prospectos_NeXo_La_Dorada.xlsx | L99: =IF($B99="","",SUBSTITUTE(INDEX(Plantillas!$B$6:$B$15,MATCH($C99,Plantillas!$A$6:$A$15,0)),"{NEGOCIO}",$B99)) | M99: =IF($B99="","",SUBSTITUTE(INDEX(Plantillas!$C$6:$C$15,MATCH($C99,Plantillas!$A$6:$A$15,0)),"{NEGOCIO}",$B99)) | N99: Pendiente de verificar | O99: Pendiente de revisar | P99: Pendiente de revisión | S99: Pendiente
A100: NX-096 | B100: HOTEL PARADOR LOS MANGOS | C100: Hoteles y hospedajes | D100: Hotel / hospedaje | F100: 3106112786 | G100: GUARINOCITO | H100: 46314 | I100: Sin señal de actualización específica en el registro fuente; verificar vigencia. | J100: https://www.datos.gov.co/w/m463-yj48/dneh-mcp2 | K100: Registro del directorio público de hoteles; confirmar vigencia y datos antes de contactar. Dirección conservada en el formato abreviado de la fuente. | Fuente: Prospectos_NeXo_La_Dorada.xlsx | L100: =IF($B100="","",SUBSTITUTE(INDEX(Plantillas!$B$6:$B$15,MATCH($C100,Plantillas!$A$6:$A$15,0)),"{NEGOCIO}",$B100)) | M100: =IF($B100="","",SUBSTITUTE(INDEX(Plantillas!$C$6:$C$15,MATCH($C100,Plantillas!$A$6:$A$15,0)),"{NEGOCIO}",$B100)) | N100: Sin correo público | O100: Pendiente de revisar | P100: Pendiente de revisión | S100: Pendiente
A101: NX-097 | B101: Hospital San Félix | C101: Salud y atención médica | D101: Salud | E101: administracion@esehospitalsanfelix.gov.co | F101: 606 857 1900 / 606 839 2000 | G101: Calle 12 #4-20, La Dorada | H101: 46314 | I101: Sin señal de actualización específica en el registro fuente; verificar vigencia. | J101: https://www.hospitalsanfelix.gov.co/images/Plan%20de%20desarrollo%202020%20hsf.pdf | https://www.funcionpublica.gov.co/ | K101: Confirmar teléfono y canal de compras/mantenimiento; datos encontrados en fuentes públicas distintas. | Fuente: Prospectos_NeXo_La_Dorada.xlsx | L101: =IF($B101="","",SUBSTITUTE(INDEX(Plantillas!$B$6:$B$15,MATCH($C101,Plantillas!$A$6:$A$15,0)),"{NEGOCIO}",$B101)) | M101: =IF($B101="","",SUBSTITUTE(INDEX(Plantillas!$C$6:$C$15,MATCH($C101,Plantillas!$A$6:$A$15,0)),"{NEGOCIO}",$B101)) | N101: Pendiente de verificar | O101: Pendiente de revisar | P101: Pendiente de revisión | S101: Pendiente
A102: NX-098 | B102: ESE Salud Dorada | C102: Salud y atención médica | D102: Salud | F102: 606 857 6950 | G102: Carrera 2 #14-37 | H102: 46314 | I102: Sin señal de actualización específica en el registro fuente; verificar vigencia. | J102: https://www.municipios.com.co/telefonos/caldas/la-dorada | K102: Teléfono y dirección en directorio municipal; verificar vigencia. | Fuente: Prospectos_NeXo_La_Dorada.xlsx | L102: =IF($B102="","",SUBSTITUTE(INDEX(Plantillas!$B$6:$B$15,MATCH($C102,Plantillas!$A$6:$A$15,0)),"{NEGOCIO}",$B102)) | M102: =IF($B102="","",SUBSTITUTE(INDEX(Plantillas!$C$6:$C$15,MATCH($C102,Plantillas!$A$6:$A$15,0)),"{NEGOCIO}",$B102)) | N102: Sin correo público | O102: Pendiente de revisar | P102: Pendiente de revisión | S102: Pendiente
A103: NX-099 | B103: Clínica de Fracturas Vita | C103: Salud y atención médica | D103: Salud | E103: gestiondocumental@clinicavita.com.co | F103: 606 839 0630 / 312 753 2965 / 314 894 6860 | G103: Calle 12 #2-03, esquina | H103: 46314 | I103: Sin señal de actualización específica en el registro fuente; verificar vigencia. | J103: https://clinicavita.com.co/ | K103: Contacto publicado en sitio oficial. | Fuente: Prospectos_NeXo_La_Dorada.xlsx | L103: =IF($B103="","",SUBSTITUTE(INDEX(Plantillas!$B$6:$B$15,MATCH($C103,Plantillas!$A$6:$A$15,0)),"{NEGOCIO}",$B103)) | M103: =IF($B103="","",SUBSTITUTE(INDEX(Plantillas!$C$6:$C$15,MATCH($C103,Plantillas!$A$6:$A$15,0)),"{NEGOCIO}",$B103)) | N103: Pendiente de verificar | O103: Pendiente de revisar | P103: Pendiente de revisión | S103: Pendiente
A104: NX-100 | B104: Clínica Flavio Restrepo | C104: Salud y atención médica | D104: Salud | E104: clinicaflavioportal@hotmail.com; archivo.cfr@gmail.com | F104: 310 430 0086 / 314 843 6493 / 312 807 1395 | G104: Consultas: Calle 12 #3-28; urgencias: Calle 13 #2-25 | H104: 46314 | I104: Sin señal de actualización específica en el registro fuente; verificar vigencia. | J104: https://www.clinicaflaviorestrepo.com/la-clinica | K104: Contacto publicado en sitio institucional. | Fuente: Prospectos_NeXo_La_Dorada.xlsx | L104: =IF($B104="","",SUBSTITUTE(INDEX(Plantillas!$B$6:$B$15,MATCH($C104,Plantillas!$A$6:$A$15,0)),"{NEGOCIO}",$B104)) | M104: =IF($B104="","",SUBSTITUTE(INDEX(Plantillas!$C$6:$C$15,MATCH($C104,Plantillas!$A$6:$A$15,0)),"{NEGOCIO}",$B104)) | N104: Pendiente de verificar | O104: Pendiente de revisar | P104: Pendiente de revisión | S104: Pendiente
A105: NX-101 | B105: DentiStar IPS | C105: Salud y atención médica | D105: Salud | E105: contacto@dentistarips.com; gerencia@dentistarips.com | F105: 310 831 6015 / 606 857 3170 | G105: Calle 12 #3-31 | H105: 46314 | I105: Sin señal de actualización específica en el registro fuente; verificar vigencia. | J105: https://www.dentistarips.com/contacto/ | K105: Contacto publicado en sitio oficial. | Fuente: Prospectos_NeXo_La_Dorada.xlsx | L105: =IF($B105="","",SUBSTITUTE(INDEX(Plantillas!$B$6:$B$15,MATCH($C105,Plantillas!$A$6:$A$15,0)),"{NEGOCIO}",$B105)) | M105: =IF($B105="","",SUBSTITUTE(INDEX(Plantillas!$C$6:$C$15,MATCH($C105,Plantillas!$A$6:$A$15,0)),"{NEGOCIO}",$B105)) | N105: Pendiente de verificar | O105: Pendiente de revisar | P105: Pendiente de revisión | S105: Pendiente
A106: NX-102 | B106: Medicare IPS | C106: Salud y atención médica | D106: Salud | E106: contacto@medicareips.com.co | F106: 321 270 1208 | G106: Calle 12 #5-31 | H106: 46314 | I106: Sin señal de actualización específica en el registro fuente; verificar vigencia. | J106: https://www.medicareips.com.co/html/info.html | K106: Contacto publicado en sitio oficial. | Fuente: Prospectos_NeXo_La_Dorada.xlsx | L106: =IF($B106="","",SUBSTITUTE(INDEX(Plantillas!$B$6:$B$15,MATCH($C106,Plantillas!$A$6:$A$15,0)),"{NEGOCIO}",$B106)) | M106: =IF($B106="","",SUBSTITUTE(INDEX(Plantillas!$C$6:$C$15,MATCH($C106,Plantillas!$A$6:$A$15,0)),"{NEGOCIO}",$B106)) | N106: Pendiente de verificar | O106: Pendiente de revisar | P106: Pendiente de revisión | S106: Pendiente
A107: NX-103 | B107: Mi IPS SAS | C107: Salud y atención médica | D107: Salud | E107: gerencia.miips@gmail.com | F107: 312 299 4274 | G107: Carrera 7 #12-24 | H107: 46314 | I107: Sin señal de actualización específica en el registro fuente; verificar vigencia. | J107: https://www.cliini.ai/herramientas/consulta-reps/1738002712 | K107: Ficha consultada en septiembre de 2026; directorios muestran un teléfono alternativo, confirmar. | Fuente: Prospectos_NeXo_La_Dorada.xlsx | L107: =IF($B107="","",SUBSTITUTE(INDEX(Plantillas!$B$6:$B$15,MATCH($C107,Plantillas!$A$6:$A$15,0)),"{NEGOCIO}",$B107)) | M107: =IF($B107="","",SUBSTITUTE(INDEX(Plantillas!$C$6:$C$15,MATCH($C107,Plantillas!$A$6:$A$15,0)),"{NEGOCIO}",$B107)) | N107: Pendiente de verificar | O107: Pendiente de revisar | P107: Pendiente de revisión | S107: Pendiente
A108: NX-104 | B108: Sociedad Unisalud | C108: Salud y atención médica | D108: Salud | E108: frontsalud@sociedadunisalud.com | F108: 606 837 4626 / 606 837 4627 / 312 299 0651 / 313 361 7861 | G108: Calle 10 #7-05 | H108: 46314 | I108: Sin señal de actualización específica en el registro fuente; verificar vigencia. | J108: https://www.sociedadunisalud.com/la-dorada/ | K108: Contacto publicado en sitio institucional. | Fuente: Prospectos_NeXo_La_Dorada.xlsx | L108: =IF($B108="","",SUBSTITUTE(INDEX(Plantillas!$B$6:$B$15,MATCH($C108,Plantillas!$A$6:$A$15,0)),"{NEGOCIO}",$B108)) | M108: =IF($B108="","",SUBSTITUTE(INDEX(Plantillas!$C$6:$C$15,MATCH($C108,Plantillas!$A$6:$A$15,0)),"{NEGOCIO}",$B108)) | N108: Pendiente de verificar | O108: Pendiente de revisar | P108: Pendiente de revisión | S108: Pendiente
A109: NX-105 | B109: Unidad de Salud y Cuidados de Altos Riesgos | C109: Salud y atención médica | D109: Salud | F109: 606 857 0481 | H109: 46314 | I109: Sin señal de actualización específica en el registro fuente; verificar vigencia. | J109: https://www.informacolombia.com/directorio-empresas/localidad_la-dorada | K109: Teléfono de directorio empresarial; confirmar razón social y vigencia. | Fuente: Prospectos_NeXo_La_Dorada.xlsx | L109: =IF($B109="","",SUBSTITUTE(INDEX(Plantillas!$B$6:$B$15,MATCH($C109,Plantillas!$A$6:$A$15,0)),"{NEGOCIO}",$B109)) | M109: =IF($B109="","",SUBSTITUTE(INDEX(Plantillas!$C$6:$C$15,MATCH($C109,Plantillas!$A$6:$A$15,0)),"{NEGOCIO}",$B109)) | N109: Sin correo público | O109: Pendiente de revisar | P109: Pendiente de revisión | S109: Pendiente
A110: NX-106 | B110: Armony | C110: Salud y atención médica | D110: Salud | F110: 322 622 6532 | H110: 46314 | I110: Sin señal de actualización específica en el registro fuente; verificar vigencia. | J110: https://www.informacolombia.com/directorio-empresas/localidad_la-dorada | K110: Teléfono de directorio empresarial; confirmar razón social y vigencia. | Fuente: Prospectos_NeXo_La_Dorada.xlsx | L110: =IF($B110="","",SUBSTITUTE(INDEX(Plantillas!$B$6:$B$15,MATCH($C110,Plantillas!$A$6:$A$15,0)),"{NEGOCIO}",$B110)) | M110: =IF($B110="","",SUBSTITUTE(INDEX(Plantillas!$C$6:$C$15,MATCH($C110,Plantillas!$A$6:$A$15,0)),"{NEGOCIO}",$B110)) | N110: Sin correo público | O110: Pendiente de revisar | P110: Pendiente de revisión | S110: Pendiente
A111: NX-107 | B111: Cámara de Comercio de La Dorada, Puerto Boyacá, Puerto Salgar y Oriente de Caldas | C111: Empresas y servicios | D111: Entidad empresarial | E111: secretaria@camaradorada.org.co | F111: 606 839 1737 / 606 839 1738; WhatsApp publicado: 322 522 4665 | G111: Calle 13 #2-24 | H111: 46314 | I111: Sin señal de actualización específica en el registro fuente; verificar vigencia. | J111: https://camaradorada.org.co/es/datos-de-acceso-oficina-principal-dorada | https://confecamaras.org.co/conozca-la-red-de-camaras-de-comercio/ | K111: Contacto institucional; no enviar publicidad por WhatsApp sin consentimiento. | Fuente: Prospectos_NeXo_La_Dorada.xlsx | L111: =IF($B111="","",SUBSTITUTE(INDEX(Plantillas!$B$6:$B$15,MATCH($C111,Plantillas!$A$6:$A$15,0)),"{NEGOCIO}",$B111)) | M111: =IF($B111="","",SUBSTITUTE(INDEX(Plantillas!$C$6:$C$15,MATCH($C111,Plantillas!$A$6:$A$15,0)),"{NEGOCIO}",$B111)) | N111: Pendiente de verificar | O111: Pendiente de revisar | P111: Pendiente de revisión | S111: Pendiente
A112: NX-108 | B112: UNAD Centro de Educación a Distancia La Dorada | C112: Educación e instituciones | D112: Educación | E112: dorada@unad.edu.co | F112: 323 264 1617 | G112: Calle 32 #1-40 | H112: 46314 | I112: Sin señal de actualización específica en el registro fuente; verificar vigencia. | J112: https://occidente.unad.edu.co/la-dorada | K112: Contacto publicado por la universidad. | Fuente: Prospectos_NeXo_La_Dorada.xlsx | L112: =IF($B112="","",SUBSTITUTE(INDEX(Plantillas!$B$6:$B$15,MATCH($C112,Plantillas!$A$6:$A$15,0)),"{NEGOCIO}",$B112)) | M112: =IF($B112="","",SUBSTITUTE(INDEX(Plantillas!$C$6:$C$15,MATCH($C112,Plantillas!$A$6:$A$15,0)),"{NEGOCIO}",$B112)) | N112: Pendiente de verificar | O112: Pendiente de revisar | P112: Pendiente de revisión | S112: Pendiente
A113: NX-109 | B113: Universidad de Caldas – Sede Magdalena Centro | C113: Educación e instituciones | D113: Educación | E113: sede.dorada@ucaldas.edu.co; ceres.dorada@ucaldas.edu.co | F113: 606 857 6540 | G113: Guarinocito, La Dorada | H113: 46314 | I113: Sin señal de actualización específica en el registro fuente; verificar vigencia. | J113: https://www.ucaldas.edu.co/portal/contactos-equipo-directivo-y-decanos/ | https://www.ucaldas.edu.co/portal/magdalena-centro/ | K113: La sede aparece en Guarinocito; confirmar correo de contacto vigente. | Fuente: Prospectos_NeXo_La_Dorada.xlsx | L113: =IF($B113="","",SUBSTITUTE(INDEX(Plantillas!$B$6:$B$15,MATCH($C113,Plantillas!$A$6:$A$15,0)),"{NEGOCIO}",$B113)) | M113: =IF($B113="","",SUBSTITUTE(INDEX(Plantillas!$C$6:$C$15,MATCH($C113,Plantillas!$A$6:$A$15,0)),"{NEGOCIO}",$B113)) | N113: Pendiente de verificar | O113: Pendiente de revisar | P113: Pendiente de revisión | S113: Pendiente
A114: NX-110 | B114: I.E. Nuestra Señora del Carmen | C114: Educación e instituciones | D114: Educación | E114: ienuestrasenioradelcarmen@gmail.com | F114: 320 483 4520 | G114: Carrera 9 con Calle 12 #12-05 | H114: 46314 | I114: Sin señal de actualización específica en el registro fuente; verificar vigencia. | J114: https://iensec.edu.co/ | K114: Contacto publicado por la institución. | Fuente: Prospectos_NeXo_La_Dorada.xlsx | L114: =IF($B114="","",SUBSTITUTE(INDEX(Plantillas!$B$6:$B$15,MATCH($C114,Plantillas!$A$6:$A$15,0)),"{NEGOCIO}",$B114)) | M114: =IF($B114="","",SUBSTITUTE(INDEX(Plantillas!$C$6:$C$15,MATCH($C114,Plantillas!$A$6:$A$15,0)),"{NEGOCIO}",$B114)) | N114: Pendiente de verificar | O114: Pendiente de revisar | P114: Pendiente de revisión | S114: Pendiente
A115: NX-111 | B115: Colegio Divino Niño Jesús | C115: Educación e instituciones | D115: Educación | E115: divino_31985@yahoo.com | F115: 323 341 3892 | G115: Carrera 4 #43-48, barrio Las Ferias | H115: 46314 | I115: Sin señal de actualización específica en el registro fuente; verificar vigencia. | J115: https://diocesisdeladorada.org/colegios-diocesanos/colegio-divino-nino-jesus/ | K115: Contacto publicado por la Diócesis. | Fuente: Prospectos_NeXo_La_Dorada.xlsx | L115: =IF($B115="","",SUBSTITUTE(INDEX(Plantillas!$B$6:$B$15,MATCH($C115,Plantillas!$A$6:$A$15,0)),"{NEGOCIO}",$B115)) | M115: =IF($B115="","",SUBSTITUTE(INDEX(Plantillas!$C$6:$C$15,MATCH($C115,Plantillas!$A$6:$A$15,0)),"{NEGOCIO}",$B115)) | N115: Pendiente de verificar | O115: Pendiente de revisar | P115: Pendiente de revisión | S115: Pendiente
A116: NX-112 | B116: Instituto Diocesano Nuevo Mundo | C116: Educación e instituciones | D116: Educación | E116: iednumladorada@gmail.com | F116: 313 627 6797 | G116: Carrera 12A #10-86 | H116: 46314 | I116: Sin señal de actualización específica en el registro fuente; verificar vigencia. | J116: https://diocesisdeladorada.org/colegios-diocesanos/instituto-diocesano-nuevo-mundo/ | K116: Contacto publicado por la Diócesis. | Fuente: Prospectos_NeXo_La_Dorada.xlsx | L116: =IF($B116="","",SUBSTITUTE(INDEX(Plantillas!$B$6:$B$15,MATCH($C116,Plantillas!$A$6:$A$15,0)),"{NEGOCIO}",$B116)) | M116: =IF($B116="","",SUBSTITUTE(INDEX(Plantillas!$C$6:$C$15,MATCH($C116,Plantillas!$A$6:$A$15,0)),"{NEGOCIO}",$B116)) | N116: Pendiente de verificar | O116: Pendiente de revisar | P116: Pendiente de revisión | S116: Pendiente
A117: NX-113 | B117: Institución Educativa Dorada | C117: Educación e instituciones | D117: Educación | F117: 606 839 0917 / 606 839 0918 | G117: Carrera 6 #3-81, avenida Los Estudiantes | H117: 46314 | I117: Sin señal de actualización específica en el registro fuente; verificar vigencia. | J117: https://sineb.mineducacion.gov.co/bcol/app?service=direct%2F0%2FHome%2F%24DirectLink&sp=IDsede%3D45731 | K117: Registro del directorio oficial SINEB; verificar canal de contacto vigente. | Fuente: Prospectos_NeXo_La_Dorada.xlsx | L117: =IF($B117="","",SUBSTITUTE(INDEX(Plantillas!$B$6:$B$15,MATCH($C117,Plantillas!$A$6:$A$15,0)),"{NEGOCIO}",$B117)) | M117: =IF($B117="","",SUBSTITUTE(INDEX(Plantillas!$C$6:$C$15,MATCH($C117,Plantillas!$A$6:$A$15,0)),"{NEGOCIO}",$B117)) | N117: Sin correo público | O117: Pendiente de revisar | P117: Pendiente de revisión | S117: Pendiente
A118: NX-114 | B118: Ferretería Electroluz | C118: Empresas y servicios | D118: Comercio / ferretería | F118: 312 288 1095 | G118: Calle 11 #7-52 | H118: 46314 | I118: Sin señal de actualización específica en el registro fuente; verificar vigencia. | J118: https://www.ferreteriaelectroluz.com/ | K118: Teléfono y dirección publicados en sitio del negocio. | Fuente: Prospectos_NeXo_La_Dorada.xlsx | L118: =IF($B118="","",SUBSTITUTE(INDEX(Plantillas!$B$6:$B$15,MATCH($C118,Plantillas!$A$6:$A$15,0)),"{NEGOCIO}",$B118)) | M118: =IF($B118="","",SUBSTITUTE(INDEX(Plantillas!$C$6:$C$15,MATCH($C118,Plantillas!$A$6:$A$15,0)),"{NEGOCIO}",$B118)) | N118: Sin correo público | O118: Pendiente de revisar | P118: Pendiente de revisión | S118: Pendiente
A119: NX-115 | B119: El Chavo Super Tienda | C119: Alimentos, tiendas y consumo | D119: Comercio / supermercado | E119: ventas@elchavosupertienda.com | F119: 310 637 0017 | G119: Calle 15 #4-25, local 5 | H119: 46314 | I119: Sin señal de actualización específica en el registro fuente; verificar vigencia. | J119: https://kwb.com.co/elchavo/ | K119: Contacto publicado en sitio de la tienda. | Fuente: Prospectos_NeXo_La_Dorada.xlsx | L119: =IF($B119="","",SUBSTITUTE(INDEX(Plantillas!$B$6:$B$15,MATCH($C119,Plantillas!$A$6:$A$15,0)),"{NEGOCIO}",$B119)) | M119: =IF($B119="","",SUBSTITUTE(INDEX(Plantillas!$C$6:$C$15,MATCH($C119,Plantillas!$A$6:$A$15,0)),"{NEGOCIO}",$B119)) | N119: Pendiente de verificar | O119: Pendiente de revisar | P119: Pendiente de revisión | S119: Pendiente
A120: NX-116 | B120: Servicentro Guarinocito Ltda | C120: Empresas y servicios | D120: Combustibles / transporte | F120: 311 720 9507 | H120: 46314 | I120: Sin señal de actualización específica en el registro fuente; verificar vigencia. | J120: https://www.informacolombia.com/directorio-empresas/localidad_la-dorada | K120: Teléfono de listado empresarial; verificar vigencia y dirección. | Fuente: Prospectos_NeXo_La_Dorada.xlsx | L120: =IF($B120="","",SUBSTITUTE(INDEX(Plantillas!$B$6:$B$15,MATCH($C120,Plantillas!$A$6:$A$15,0)),"{NEGOCIO}",$B120)) | M120: =IF($B120="","",SUBSTITUTE(INDEX(Plantillas!$C$6:$C$15,MATCH($C120,Plantillas!$A$6:$A$15,0)),"{NEGOCIO}",$B120)) | N120: Sin correo público | O120: Pendiente de revisar | P120: Pendiente de revisión | S120: Pendiente
A121: NX-117 | B121: Distribuidora Vidal Ltda | C121: Empresas y servicios | D121: Comercio / distribución | F121: 311 202 3595 | H121: 46314 | I121: Sin señal de actualización específica en el registro fuente; verificar vigencia. | J121: https://www.informacolombia.com/directorio-empresas/localidad_la-dorada | K121: Comparte número con la ficha hotelera Balcones de San Diego; confirmar relación. | Fuente: Prospectos_NeXo_La_Dorada.xlsx | L121: =IF($B121="","",SUBSTITUTE(INDEX(Plantillas!$B$6:$B$15,MATCH($C121,Plantillas!$A$6:$A$15,0)),"{NEGOCIO}",$B121)) | M121: =IF($B121="","",SUBSTITUTE(INDEX(Plantillas!$C$6:$C$15,MATCH($C121,Plantillas!$A$6:$A$15,0)),"{NEGOCIO}",$B121)) | N121: Sin correo público | O121: Pendiente de revisar | P121: Pendiente de revisión | S121: Pendiente
A122: NX-118 | B122: Suganado Comercializadora SAS | C122: Empresas y servicios | D122: Comercio / agro | F122: 314 270 1406 | H122: 46314 | I122: Sin señal de actualización específica en el registro fuente; verificar vigencia. | J122: https://www.informacolombia.com/directorio-empresas/localidad_la-dorada | K122: Teléfono de listado empresarial; verificar vigencia y dirección. | Fuente: Prospectos_NeXo_La_Dorada.xlsx | L122: =IF($B122="","",SUBSTITUTE(INDEX(Plantillas!$B$6:$B$15,MATCH($C122,Plantillas!$A$6:$A$15,0)),"{NEGOCIO}",$B122)) | M122: =IF($B122="","",SUBSTITUTE(INDEX(Plantillas!$C$6:$C$15,MATCH($C122,Plantillas!$A$6:$A$15,0)),"{NEGOCIO}",$B122)) | N122: Sin correo público | O122: Pendiente de revisar | P122: Pendiente de revisión | S122: Pendiente
A123: NX-119 | B123: Distriheber A y G SAS | C123: Empresas y servicios | D123: Comercio / distribución | F123: 606 839 0401 | H123: 46314 | I123: Sin señal de actualización específica en el registro fuente; verificar vigencia. | J123: https://www.informacolombia.com/directorio-empresas/localidad_la-dorada | K123: Teléfono de listado empresarial; verificar vigencia y dirección. | Fuente: Prospectos_NeXo_La_Dorada.xlsx | L123: =IF($B123="","",SUBSTITUTE(INDEX(Plantillas!$B$6:$B$15,MATCH($C123,Plantillas!$A$6:$A$15,0)),"{NEGOCIO}",$B123)) | M123: =IF($B123="","",SUBSTITUTE(INDEX(Plantillas!$C$6:$C$15,MATCH($C123,Plantillas!$A$6:$A$15,0)),"{NEGOCIO}",$B123)) | N123: Sin correo público | O123: Pendiente de revisar | P123: Pendiente de revisión | S123: Pendiente
A124: NX-120 | B124: Fácil Créditos SAS | C124: Empresas y servicios | D124: Finanzas | F124: 323 473 4032 | H124: 46314 | I124: Sin señal de actualización específica en el registro fuente; verificar vigencia. | J124: https://www.informacolombia.com/directorio-empresas/localidad_la-dorada | K124: Teléfono de listado empresarial; verificar vigencia y dirección. | Fuente: Prospectos_NeXo_La_Dorada.xlsx | L124: =IF($B124="","",SUBSTITUTE(INDEX(Plantillas!$B$6:$B$15,MATCH($C124,Plantillas!$A$6:$A$15,0)),"{NEGOCIO}",$B124)) | M124: =IF($B124="","",SUBSTITUTE(INDEX(Plantillas!$C$6:$C$15,MATCH($C124,Plantillas!$A$6:$A$15,0)),"{NEGOCIO}",$B124)) | N124: Sin correo público | O124: Pendiente de revisar | P124: Pendiente de revisión | S124: Pendiente
A125: NX-121 | B125: Motos La Gran Parada SAS | C125: Empresas y servicios | D125: Comercio / motocicletas | F125: 606 837 0352 | H125: 46314 | I125: Sin señal de actualización específica en el registro fuente; verificar vigencia. | J125: https://www.informacolombia.com/directorio-empresas/localidad_la-dorada | K125: Teléfono de listado empresarial; verificar vigencia y dirección. | Fuente: Prospectos_NeXo_La_Dorada.xlsx | L125: =IF($B125="","",SUBSTITUTE(INDEX(Plantillas!$B$6:$B$15,MATCH($C125,Plantillas!$A$6:$A$15,0)),"{NEGOCIO}",$B125)) | M125: =IF($B125="","",SUBSTITUTE(INDEX(Plantillas!$C$6:$C$15,MATCH($C125,Plantillas!$A$6:$A$15,0)),"{NEGOCIO}",$B125)) | N125: Sin correo público | O125: Pendiente de revisar | P125: Pendiente de revisión | S125: Pendiente
A126: NX-122 | B126: CDA Divecol Ltda | C126: Empresas y servicios | D126: Automotor / revisión técnico-mecánica | F126: 304 617 2880 | H126: 46314 | I126: Sin señal de actualización específica en el registro fuente; verificar vigencia. | J126: https://www.informacolombia.com/directorio-empresas/localidad_la-dorada | K126: Teléfono de listado empresarial; verificar vigencia y dirección. | Fuente: Prospectos_NeXo_La_Dorada.xlsx | L126: =IF($B126="","",SUBSTITUTE(INDEX(Plantillas!$B$6:$B$15,MATCH($C126,Plantillas!$A$6:$A$15,0)),"{NEGOCIO}",$B126)) | M126: =IF($B126="","",SUBSTITUTE(INDEX(Plantillas!$C$6:$C$15,MATCH($C126,Plantillas!$A$6:$A$15,0)),"{NEGOCIO}",$B126)) | N126: Sin correo público | O126: Pendiente de revisar | P126: Pendiente de revisión | S126: Pendiente
A127: NX-123 | B127: JV Inversiones JHLV SAS | C127: Empresas y servicios | D127: Inversiones / servicios | F127: 313 403 5440 | H127: 46314 | I127: Sin señal de actualización específica en el registro fuente; verificar vigencia. | J127: https://www.informacolombia.com/directorio-empresas/localidad_la-dorada | K127: Teléfono de listado empresarial; verificar vigencia y dirección. | Fuente: Prospectos_NeXo_La_Dorada.xlsx | L127: =IF($B127="","",SUBSTITUTE(INDEX(Plantillas!$B$6:$B$15,MATCH($C127,Plantillas!$A$6:$A$15,0)),"{NEGOCIO}",$B127)) | M127: =IF($B127="","",SUBSTITUTE(INDEX(Plantillas!$C$6:$C$15,MATCH($C127,Plantillas!$A$6:$A$15,0)),"{NEGOCIO}",$B127)) | N127: Sin correo público | O127: Pendiente de revisar | P127: Pendiente de revisión | S127: Pendiente
A128: NX-124 | B128: Suministros y Logística de Oriente SAS | C128: Empresas y servicios | D128: Comercio / logística | F128: 310 369 9499 | H128: 46314 | I128: Sin señal de actualización específica en el registro fuente; verificar vigencia. | J128: https://www.informacolombia.com/directorio-empresas/localidad_la-dorada | K128: Teléfono de listado empresarial; verificar vigencia y dirección. | Fuente: Prospectos_NeXo_La_Dorada.xlsx | L128: =IF($B128="","",SUBSTITUTE(INDEX(Plantillas!$B$6:$B$15,MATCH($C128,Plantillas!$A$6:$A$15,0)),"{NEGOCIO}",$B128)) | M128: =IF($B128="","",SUBSTITUTE(INDEX(Plantillas!$C$6:$C$15,MATCH($C128,Plantillas!$A$6:$A$15,0)),"{NEGOCIO}",$B128)) | N128: Sin correo público | O128: Pendiente de revisar | P128: Pendiente de revisión | S128: Pendiente
A129: NX-125 | B129: Inversiones Paguemenos La Dorada SAS | C129: Empresas y servicios | D129: Comercio | F129: 322 361 4606 | H129: 46314 | I129: Sin señal de actualización específica en el registro fuente; verificar vigencia. | J129: https://www.informacolombia.com/directorio-empresas/localidad_la-dorada | K129: Teléfono de listado empresarial; verificar vigencia y dirección. | Fuente: Prospectos_NeXo_La_Dorada.xlsx | L129: =IF($B129="","",SUBSTITUTE(INDEX(Plantillas!$B$6:$B$15,MATCH($C129,Plantillas!$A$6:$A$15,0)),"{NEGOCIO}",$B129)) | M129: =IF($B129="","",SUBSTITUTE(INDEX(Plantillas!$C$6:$C$15,MATCH($C129,Plantillas!$A$6:$A$15,0)),"{NEGOCIO}",$B129)) | N129: Sin correo público | O129: Pendiente de revisar | P129: Pendiente de revisión | S129: Pendiente
A130: NX-126 | B130: Hernando Jaramillo e Hijos Ltda | C130: Empresas y servicios | D130: Comercio / servicios | F130: 310 436 9744 | H130: 46314 | I130: Sin señal de actualización específica en el registro fuente; verificar vigencia. | J130: https://www.informacolombia.com/directorio-empresas/localidad_la-dorada | K130: Teléfono de listado empresarial; verificar vigencia y dirección. | Fuente: Prospectos_NeXo_La_Dorada.xlsx | L130: =IF($B130="","",SUBSTITUTE(INDEX(Plantillas!$B$6:$B$15,MATCH($C130,Plantillas!$A$6:$A$15,0)),"{NEGOCIO}",$B130)) | M130: =IF($B130="","",SUBSTITUTE(INDEX(Plantillas!$C$6:$C$15,MATCH($C130,Plantillas!$A$6:$A$15,0)),"{NEGOCIO}",$B130)) | N130: Sin correo público | O130: Pendiente de revisar | P130: Pendiente de revisión | S130: Pendiente
A131: NX-127 | B131: Metromax Supermercados 4 La Dorada SAS | C131: Alimentos, tiendas y consumo | D131: Comercio / supermercado | F131: 313 851 7524 | H131: 46314 | I131: Sin señal de actualización específica en el registro fuente; verificar vigencia. | J131: https://www.informacolombia.com/directorio-empresas/localidad_la-dorada | K131: Teléfono de listado empresarial; verificar vigencia y dirección. | Fuente: Prospectos_NeXo_La_Dorada.xlsx | L131: =IF($B131="","",SUBSTITUTE(INDEX(Plantillas!$B$6:$B$15,MATCH($C131,Plantillas!$A$6:$A$15,0)),"{NEGOCIO}",$B131)) | M131: =IF($B131="","",SUBSTITUTE(INDEX(Plantillas!$C$6:$C$15,MATCH($C131,Plantillas!$A$6:$A$15,0)),"{NEGOCIO}",$B131)) | N131: Sin correo público | O131: Pendiente de revisar | P131: Pendiente de revisión | S131: Pendiente
... A139: NX-135 | B139: Sociedad Alfa TV Dorada y Compañía SA | C139: Empresas y servicios | D139: Medios / telecomunicaciones | F139: 313 624 1587 | H139: 46314 | I139: Sin señal de actualización específica en el registro fuente; verificar vigencia. | J139: https://www.informacolombia.com/directorio-empresas/localidad_la-dorada | K139: Teléfono de listado empresarial; verificar vigencia y dirección. | Fuente: Prospectos_NeXo_La_Dorada.xlsx | L139: =IF($B139="","",SUBSTITUTE(INDEX(Plantillas!$B$6:$B$15,MATCH($C139,Plantillas!$A$6:$A$15,0)),"{NEGOCIO}",$B139)) | M139: =IF($B139="","",SUBSTITUTE(INDEX(Plantillas!$C$6:$C$15,MATCH($C139,Plantillas!$A$6:$A$15,0)),"{NEGOCIO}",$B139)) | N139: Sin correo público | O139: Pendiente de revisar | P139: Pendiente de revisión | S139: Pendiente
A140: NX-136 | B140: Papelería Comercial | C140: Papelerías, copias e impresión | D140: Papelería / copias | F140: 310 521 4687 | G140: Calle 14 #3-2 | H140: 46314 | I140: Ficha Waze rastreada hace ~1 mes (oct. 2026); confirmar por teléfono. | J140: https://www.waze.com/live-map/directions/co/caldas/la-dorada/papeleria-comercial?to=place.ChIJD0tEeKLeQI4Rfxk_uAbJiiE | K140: Fuente: Prospectos_NeXo_La_Dorada_Ampliacion.xlsx | L140: =IF($B140="","",SUBSTITUTE(INDEX(Plantillas!$B$6:$B$15,MATCH($C140,Plantillas!$A$6:$A$15,0)),"{NEGOCIO}",$B140)) | M140: =IF($B140="","",SUBSTITUTE(INDEX(Plantillas!$C$6:$C$15,MATCH($C140,Plantillas!$A$6:$A$15,0)),"{NEGOCIO}",$B140)) | N140: Sin correo público | O140: Pendiente de revisar | P140: Pendiente de revisión | S140: Pendiente
A141: NX-137 | B141: Papelería El Editor | C141: Papelerías, copias e impresión | D141: Papelería / copias | F141: 320 535 5911 | G141: Carrera 6 #12-44 | H141: 46314 | I141: Ficha Waze rastreada hace ~2 meses; confirmar vigencia. | J141: https://www.waze.com/es/live-map/directions/co/caldas/la-dorada/papeleria-el-editor?to=place.ChIJg0lQJ6LeQI4RExMDrSwMVrc | K141: Fuente: Prospectos_NeXo_La_Dorada_Ampliacion.xlsx | L141: =IF($B141="","",SUBSTITUTE(INDEX(Plantillas!$B$6:$B$15,MATCH($C141,Plantillas!$A$6:$A$15,0)),"{NEGOCIO}",$B141)) | M141: =IF($B141="","",SUBSTITUTE(INDEX(Plantillas!$C$6:$C$15,MATCH($C141,Plantillas!$A$6:$A$15,0)),"{NEGOCIO}",$B141)) | N141: Sin correo público | O141: Pendiente de revisar | P141: Pendiente de revisión | S141: Pendiente
A142: NX-138 | B142: Papelería Dónde Marce | C142: Papelerías, copias e impresión | D142: Papelería / corresponsal | F142: 323 378 4800 | G142: Carrera 5 #17-47 | H142: 46314 | I142: Directorio consultado hace ~3 meses; dirección también aparece en listado de corresponsales ene. 2026. | J142: https://co.todosnegocios.com/papeler%C3%ADa-d%C3%B3nde-marce-323-378-4800 | https://www.bancoagrario.gov.co/system/files/2026-01/supergiros_0.pdf | https://www.bancoagrario.gov.co/canales-de-atencion/corresponsales | K142: Fuente: Prospectos_NeXo_La_Dorada_Ampliacion.xlsx | L142: =IF($B142="","",SUBSTITUTE(INDEX(Plantillas!$B$6:$B$15,MATCH($C142,Plantillas!$A$6:$A$15,0)),"{NEGOCIO}",$B142)) | M142: =IF($B142="","",SUBSTITUTE(INDEX(Plantillas!$C$6:$C$15,MATCH($C142,Plantillas!$A$6:$A$15,0)),"{NEGOCIO}",$B142)) | N142: Sin correo público | O142: Pendiente de revisar | P142: Pendiente de revisión | S142: Pendiente
A143: NX-139 | B143: Litografía Dorada | C143: Papelerías, copias e impresión | D143: Papelería / impresión | F143: 606 857 2370 | G143: Carrera 3 #11-82 | H143: 46314 | I143: Directorios rastreados hace 4–5 meses; validar si sigue activa. | J143: https://www.nexdu.com/co/la-dorada-cal/empresa/litografia-dorada-394530 | https://www.paginasamarillas.com.co/la-dorada/servicios/papel-imprenta-y-editorial-a-domicilio | K143: Fuente: Prospectos_NeXo_La_Dorada_Ampliacion.xlsx | L143: =IF($B143="","",SUBSTITUTE(INDEX(Plantillas!$B$6:$B$15,MATCH($C143,Plantillas!$A$6:$A$15,0)),"{NEGOCIO}",$B143)) | M143: =IF($B143="","",SUBSTITUTE(INDEX(Plantillas!$C$6:$C$15,MATCH($C143,Plantillas!$A$6:$A$15,0)),"{NEGOCIO}",$B143)) | N143: Sin correo público | O143: Pendiente de revisar | P143: Pendiente de revisión | S143: Pendiente
A144: NX-140 | B144: Papelería La Americana | C144: Papelerías, copias e impresión | D144: Papelería / impresión | F144: 606 857 8211 | G144: Calle 14 #1-12 | H144: 46314 | I144: Ficha de Páginas Amarillas rastreada hace ~4 meses; dato histórico en otros directorios. | J144: https://www.paginasamarillas.com.co/empresas/papeleria-la-americana/la-dorada-15441724?ad=50165522 | https://www.direccion.com.co/lugar/la-dorada/papeleria-la-americana/ | K144: Fuente: Prospectos_NeXo_La_Dorada_Ampliacion.xlsx | L144: =IF($B144="","",SUBSTITUTE(INDEX(Plantillas!$B$6:$B$15,MATCH($C144,Plantillas!$A$6:$A$15,0)),"{NEGOCIO}",$B144)) | M144: =IF($B144="","",SUBSTITUTE(INDEX(Plantillas!$C$6:$C$15,MATCH($C144,Plantillas!$A$6:$A$15,0)),"{NEGOCIO}",$B144)) | N144: Sin correo público | O144: Pendiente de revisar | P144: Pendiente de revisión | S144: Pendiente
A145: NX-141 | B145: Papelería Gufi | C145: Papelerías, copias e impresión | D145: Papelería / copias | F145: 606 839 0983 | G145: Carrera 6 #5-58, Los Alpes | H145: 46314 | I145: Directorio rastreado hace ~4 meses; dirección difiere de un pin de Waze (Cra. 6 #6-34), confirmar. | J145: https://www.paginasamarillas.com.co/la-dorada/servicios/papel-imprenta-y-editorial-a-domicilio | https://www.waze.com/es/live-map/directions/co/caldas/la-dorada/papeleria-gufi?to=place.ChIJjfDCrJPfQI4RKiwotf6Aop4 | K145: Fuente: Prospectos_NeXo_La_Dorada_Ampliacion.xlsx | L145: =IF($B145="","",SUBSTITUTE(INDEX(Plantillas!$B$6:$B$15,MATCH($C145,Plantillas!$A$6:$A$15,0)),"{NEGOCIO}",$B145)) | M145: =IF($B145="","",SUBSTITUTE(INDEX(Plantillas!$C$6:$C$15,MATCH($C145,Plantillas!$A$6:$A$15,0)),"{NEGOCIO}",$B145)) | N145: Sin correo público | O145: Pendiente de revisar | P145: Pendiente de revisión | S145: Pendiente
A146: NX-142 | B146: Multiservicios Doble A | C146: Papelerías, copias e impresión | D146: Papelería / corresponsal / soporte técnico | F146: 314 681 8087 | G146: Carrera 3 #13-17 | H146: 46314 | I146: Página del negocio rastreada la semana de consulta (oct. 2026). | J146: https://multiservicios-doble-a.ueniweb.com/ | K146: Fuente: Prospectos_NeXo_La_Dorada_Ampliacion.xlsx | L146: =IF($B146="","",SUBSTITUTE(INDEX(Plantillas!$B$6:$B$15,MATCH($C146,Plantillas!$A$6:$A$15,0)),"{NEGOCIO}",$B146)) | M146: =IF($B146="","",SUBSTITUTE(INDEX(Plantillas!$C$6:$C$15,MATCH($C146,Plantillas!$A$6:$A$15,0)),"{NEGOCIO}",$B146)) | N146: Sin correo público | O146: Pendiente de revisar | P146: Pendiente de revisión | S146: Pendiente
A147: NX-143 | B147: Papelería y Accesorios Nanda Steel | C147: Papelerías, copias e impresión | D147: Papelería / corresponsal | G147: Centro Comercial Dorada Plaza, local N107-2 | H147: 46314 | I147: Ficha de Vía Baloto rastreada hace ~1 semana; no publica teléfono. | J147: https://libreroonline.com/via-baloto/caldas/la-dorada/5558/papeleria-y-accesorios-nanda-steel/ | K147: Fuente: Prospectos_NeXo_La_Dorada_Ampliacion.xlsx | L147: =IF($B147="","",SUBSTITUTE(INDEX(Plantillas!$B$6:$B$15,MATCH($C147,Plantillas!$A$6:$A$15,0)),"{NEGOCIO}",$B147)) | M147: =IF($B147="","",SUBSTITUTE(INDEX(Plantillas!$C$6:$C$15,MATCH($C147,Plantillas!$A$6:$A$15,0)),"{NEGOCIO}",$B147)) | N147: Sin correo público | O147: Pendiente de revisar | P147: Pendiente de revisión | S147: Pendiente
A148: NX-144 | B148: Tienda Cristiana Luz y Verdad | C148: Papelerías, copias e impresión | D148: Librería / papelería | F148: 606 857 0821 / 314 789 7012 / 314 695 5998 | G148: Calle 15 #4-30, C.C. Dorada Plaza, local S106-4 | H148: 46314 | I148: Ficha rastreada hace ~1 mes; directorio de terceros. | J148: https://www.aiyellow.com/tienda-cristiana-dorada-caldas/ | K148: Fuente: Prospectos_NeXo_La_Dorada_Ampliacion.xlsx | L148: =IF($B148="","",SUBSTITUTE(INDEX(Plantillas!$B$6:$B$15,MATCH($C148,Plantillas!$A$6:$A$15,0)),"{NEGOCIO}",$B148)) | M148: =IF($B148="","",SUBSTITUTE(INDEX(Plantillas!$C$6:$C$15,MATCH($C148,Plantillas!$A$6:$A$15,0)),"{NEGOCIO}",$B148)) | N148: Sin correo público | O148: Pendiente de revisar | P148: Pendiente de revisión | S148: Pendiente
A149: NX-145 | B149: LR Soluciones Group SAS | C149: Papelerías, copias e impresión | D149: Papelería / artículos de oficina | F149: 310 734 3903 | G149: Carrera 2B #46A-03 | H149: 46314 | I149: Directorio empresarial rastreado hace ~3 meses; verificar local y teléfono. | J149: https://www.informacion-empresas.co/Empresa_BGM-SOLUCIONES-INTEGRALES-SAS.html | K149: Fuente: Prospectos_NeXo_La_Dorada_Ampliacion.xlsx | L149: =IF($B149="","",SUBSTITUTE(INDEX(Plantillas!$B$6:$B$15,MATCH($C149,Plantillas!$A$6:$A$15,0)),"{NEGOCIO}",$B149)) | M149: =IF($B149="","",SUBSTITUTE(INDEX(Plantillas!$C$6:$C$15,MATCH($C149,Plantillas!$A$6:$A$15,0)),"{NEGOCIO}",$B149)) | N149: Sin correo público | O149: Pendiente de revisar | P149: Pendiente de revisión | S149: Pendiente
...

Sheet Plantillas
A2: Plantillas de correo por sector
A3: Edita aquí; {NEGOCIO} se reemplaza automáticamente en Contactos.
A5: Categoría de contacto | B5: Asunto modelo | C5: Cuerpo modelo (texto plano) | D5: Sectores incluidos
A6: Hoteles y hospedajes | B6: Soporte para impresoras y computadores en {NEGOCIO} | C6: Hola, equipo de {NEGOCIO}: Somos NeXo, una empresa tecnológica de La Dorada. Apoyamos a hoteles y hospedajes con mantenimiento y reparación de impresoras de distintas marcas y tecnologías, soporte para computadores e insumos de impresión. También desarrollamos páginas web y automatizaciones que pueden ayudar a organizar procesos del negocio. ¿Quién coordina el soporte de estos equipos? Si les interesa, podemos presentarnos y coordinar una visita breve para conocer sus necesidades. Atentamente, Equipo NeXo Soluciones tecnológicas y servicio técnico | La Dorada, Caldas WhatsApp: +57 322 206 7870 Sitio web: https://ne-xo-page.vercel.app Si prefieren no recibir más información comercial, pueden responder a este correo y lo tendremos en cuenta. | D6: Hoteles, hospedajes, apartahoteles y alojamientos.
A7: Salud y atención médica | B7: Mantenimiento tecnológico para {NEGOCIO} | C7: Cordial saludo, equipo de {NEGOCIO}: Somos NeXo, empresa tecnológica de La Dorada. Ofrecemos mantenimiento preventivo y correctivo de impresoras láser, de tinta y multifuncionales, además de soporte para computadores. Podemos coordinar la atención para conocer sus equipos y las necesidades de su área administrativa. ¿Quién coordina el mantenimiento de impresoras y computadores en la institución? Nos gustaría presentarles nuestros servicios y acordar una visita breve, si lo consideran conveniente. Atentamente, Equipo NeXo Soluciones tecnológicas y servicio técnico | La Dorada, Caldas WhatsApp: +57 322 206 7870 Sitio web: https://ne-xo-page.vercel.app Si prefieren no recibir más información comercial, pueden responder a este correo y lo tendremos en cuenta. | D7: Hospitales, clínicas, centros médicos, odontología y prestadores de salud.
A8: Educación e instituciones | B8: Soporte de impresión y computadores para {NEGOCIO} | C8: Cordial saludo, equipo de {NEGOCIO}: Somos NeXo, una empresa tecnológica de La Dorada. Brindamos mantenimiento y reparación de impresoras de diferentes marcas y tecnologías, y soporte para computadores portátiles y de escritorio. También desarrollamos páginas web, software y automatizaciones para apoyar procesos institucionales. ¿Quién coordina el mantenimiento de estos equipos? Nos gustaría presentarles nuestros servicios y, si les resulta útil, coordinar una visita breve. Atentamente, Equipo NeXo Soluciones tecnológicas y servicio técnico | La Dorada, Caldas WhatsApp: +57 322 206 7870 Sitio web: https://ne-xo-page.vercel.app Si prefieren no recibir más información comercial, pueden responder a este correo y lo tendremos en cuenta. | D8: Instituciones educativas, colegios y universidades.
A9: Papelerías, copias e impresión | B9: Aliado técnico para impresión e insumos | NeXo | C9: Hola, equipo de {NEGOCIO}: Somos NeXo, empresa tecnológica de La Dorada. Ofrecemos mantenimiento y reparación de impresoras láser, de tinta continua, de cartucho y multifuncionales. También contamos con insumos para impresión a precios competitivos y brindamos soporte a computadores. Nos gustaría conocer sus necesidades y presentarles opciones para apoyar la operación de su negocio. ¿Con quién podríamos coordinar una conversación o visita breve? Atentamente, Equipo NeXo Soluciones tecnológicas y servicio técnico | La Dorada, Caldas WhatsApp: +57 322 206 7870 Sitio web: https://ne-xo-page.vercel.app Si prefieren no recibir más información comercial, pueden responder a este correo y lo tendremos en cuenta. | D9: Papelerías, librerías, copiado, litografía, impresión y publicidad impresa.
A10: Belleza y cuidado personal | B10: Apoyo tecnológico para {NEGOCIO} | C10: Hola, equipo de {NEGOCIO}: Somos NeXo, empresa tecnológica de La Dorada. Si en su negocio utilizan computadores o impresoras para la atención y administración, podemos apoyarles con diagnóstico, mantenimiento y reparación. También creamos páginas web y automatizaciones a la medida para negocios y empresas. ¿Quién coordina estos temas? Si les parece, podemos conversar brevemente y explorar qué solución les sería útil. Atentamente, Equipo NeXo Soluciones tecnológicas y servicio técnico | La Dorada, Caldas WhatsApp: +57 322 206 7870 Sitio web: https://ne-xo-page.vercel.app Si prefieren no recibir más información comercial, pueden responder a este correo y lo tendremos en cuenta. | D10: Peluquerías, barberías, uñas, spa, pestañas, cosmética y belleza.
A11: Moda, calzado y accesorios | B11: Servicios tecnológicos para {NEGOCIO} | C11: Hola, equipo de {NEGOCIO}: Somos NeXo, empresa tecnológica de La Dorada. Brindamos mantenimiento y soporte para impresoras y computadores, y desarrollamos páginas web, software y automatizaciones para negocios. Podemos conocer sus necesidades y proponer opciones prácticas para sus procesos administrativos y su presencia digital. ¿Con quién podríamos conversar sobre el soporte tecnológico de su negocio? Estamos disponibles para una presentación breve. Atentamente, Equipo NeXo Soluciones tecnológicas y servicio técnico | La Dorada, Caldas WhatsApp: +57 322 206 7870 Sitio web: https://ne-xo-page.vercel.app Si prefieren no recibir más información comercial, pueden responder a este correo y lo tendremos en cuenta. | D11: Boutiques, ropa, calzado, accesorios, talabarterías y sastrerías.
A12: Alimentos, tiendas y consumo | B12: Soporte para computadores e impresión en {NEGOCIO} | C12: Hola, equipo de {NEGOCIO}: Somos NeXo, una empresa tecnológica de La Dorada. Ofrecemos mantenimiento y reparación de impresoras y soporte para computadores. Además, desarrollamos páginas web, software y automatizaciones ajustadas a las necesidades de cada negocio. ¿Quién coordina el soporte tecnológico? Nos gustaría presentarles nuestros servicios y saber si podemos ayudarles con algún equipo o proceso. Atentamente, Equipo NeXo Soluciones tecnológicas y servicio técnico | La Dorada, Caldas WhatsApp: +57 322 206 7870 Sitio web: https://ne-xo-page.vercel.app Si prefieren no recibir más información comercial, pueden responder a este correo y lo tendremos en cuenta. | D12: Tiendas, supermercados, panaderías, alimentos y comercios de consumo.
A13: Comercios y corresponsales | B13: Soluciones tecnológicas para {NEGOCIO} | C13: Hola, equipo de {NEGOCIO}: Somos NeXo, empresa tecnológica de La Dorada. Apoyamos a negocios locales con mantenimiento de impresoras, soporte para computadores y suministro de insumos de impresión. También desarrollamos páginas web, software y automatizaciones a la medida. ¿Quién coordina estos servicios en su negocio? Podemos presentarnos y conocer sus necesidades en una conversación breve. Atentamente, Equipo NeXo Soluciones tecnológicas y servicio técnico | La Dorada, Caldas WhatsApp: +57 322 206 7870 Sitio web: https://ne-xo-page.vercel.app Si prefieren no recibir más información comercial, pueden responder a este correo y lo tendremos en cuenta. | D13: Corresponsales, misceláneas, variedades, tiendas y comercio minorista.
A14: Bienestar y entrenamiento | B14: Soporte digital y tecnológico para {NEGOCIO} | C14: Hola, equipo de {NEGOCIO}: Somos NeXo, una empresa tecnológica de La Dorada. Ofrecemos soporte para computadores e impresoras y creamos páginas web y automatizaciones que pueden ayudar a organizar procesos de negocios dedicados al bienestar y el entrenamiento. ¿Quién coordina el soporte tecnológico o los proyectos digitales? Nos gustaría presentarles brevemente nuestros servicios y conocer sus necesidades. Atentamente, Equipo NeXo Soluciones tecnológicas y servicio técnico | La Dorada, Caldas WhatsApp: +57 322 206 7870 Sitio web: https://ne-xo-page.vercel.app Si prefieren no recibir más información comercial, pueden responder a este correo y lo tendremos en cuenta. | D14: Gimnasios, entrenamiento y bienestar.
A15: Empresas y servicios | B15: Presentación de servicios tecnológicos | NeXo | C15: Cordial saludo, equipo de {NEGOCIO}: Somos NeXo, una empresa tecnológica de La Dorada. Prestamos mantenimiento y reparación de impresoras de distintas marcas y tecnologías, soporte para computadores, y desarrollamos software, páginas web y automatizaciones para empresas e instituciones. ¿Quién coordina el soporte de impresoras y computadores o los proyectos de tecnología? Nos gustaría presentarles nuestros servicios y conocer sus necesidades. Atentamente, Equipo NeXo Soluciones tecnológicas y servicio técnico | La Dorada, Caldas WhatsApp: +57 322 206 7870 Sitio web: https://ne-xo-page.vercel.app Si prefieren no recibir más información comercial, pueden responder a este correo y lo tendremos en cuenta. | D15: Empresas, servicios profesionales, comercio mayorista, transporte, construcción, finanzas, logística y otros sectores.

Sheet Clasificación
A2: Mapa de categorías
A3: Referencia editable: cada sector de origen se agrupa en una categoría para filtrar la base. Si una clasificación no encaja, cambia la categoría en Contactos.
A5: Sector según fuente | B5: Categoría de contacto | C5: Negocios en esta categoría fuente
A6: Accesorios / ropa | B6: Moda, calzado y accesorios | C6: 1
A7: Alimentos / corresponsal | B7: Alimentos, tiendas y consumo | C7: 1
A8: Alimentos / repostería | B8: Alimentos, tiendas y consumo | C8: 1
A9: Automotor / revisión técnico-mecánica | B9: Empresas y servicios | C9: 1
A10: Barbería | B10: Belleza y cuidado personal | C10: 6
A11: Belleza / cosméticos / accesorios | B11: Belleza y cuidado personal | C11: 1
A12: Belleza / peluquería | B12: Belleza y cuidado personal | C12: 1
A13: Belleza / pestañas | B13: Belleza y cuidado personal | C13: 1
A14: Belleza / spa | B14: Belleza y cuidado personal | C14: 1
A15: Belleza / uñas | B15: Belleza y cuidado personal | C15: 4
A16: Belleza / uñas / peluquería | B16: Belleza y cuidado personal | C16: 1
A17: Calzado / zapatería | B17: Moda, calzado y accesorios | C17: 2
... A74: Variedades / corresponsal | B74: Comercios y corresponsales | C74: 6
